Workbook

Sheet Raw Data
A1: Row ID | B1: Order ID | C1: Order Date | D1: Ship Date | E1: Ship Mode | F1: Customer ID | G1: Customer Name | H1: Segment | I1: Country | J1: City | K1: State | L1: Postal Code | M1: Region | N1: Product ID | O1: Category | P1: Sub-Category | Q1: Product Name | R1: Sales | S1: Quantity | T1: Discount | U1: Profit | V1: Order Date Fixed
A2: 1 | B2: CA-2016-152156 | C2: 42593 | D2: 42685 | E2: Second Class | F2: CG-12520 | G2: Claire Gute | H2: Consumer | I2: United States | J2: Henderson | K2: Kentucky | L2: 42420 | M2: South | N2: FUR-BO-10001798 | O2: Furniture | P2: Bookcases | Q2: Bush Somerset Collection Bookcase | R2: 261.96 | S2: 2 | T2: 0 | U2: 41.9136 | V2: =IF(ISNUMBER(SalesData[[#This Row],[Order Date]]),DATE(YEAR(SalesData[[#This Row],[Order Date]]),DAY(SalesData[[#This Row],[Order Date]]),MONTH(SalesData[[#This Row],[Order Date]])),DATE(VALUE(RIGHT(SalesData[[#This Row],[Order Date]],4)),VALUE(LEFT(SalesData[[#This Row],[Order Date]],FIND("/",SalesData[[#This Row],[Order Date]])-1)),VALUE(MID(SalesData[[#This Row],[Order Date]],FIND("/",SalesData[[#This Row],[Order Date]])+1,FIND("/",SalesData[[#This Row],[Order Date]],FIND("/",SalesData[[#This Row],[Order Date]])+1)-FIND("/",SalesData[[#This Row],[Order Date]])-1)))) -> 42682
A3: 2 | B3: CA-2016-152156 | C3: 42593 | D3: 42685 | E3: Second Class | F3: CG-12520 | G3: Claire Gute | H3: Consumer | I3: United States | J3: Henderson | K3: Kentucky | L3: 42420 | M3: South | N3: FUR-CH-10000454 | O3: Furniture | P3: Chairs | Q3: Hon Deluxe Fabric Upholstered Stacking Chairs, Rounded Back | R3: 731.94 | S3: 3 | T3: 0 | U3: 219.582 | V3: =IF(ISNUMBER(SalesData[[#This Row],[Order Date]]),DATE(YEAR(SalesData[[#This Row],[Order Date]]),DAY(SalesData[[#This Row],[Order Date]]),MONTH(SalesData[[#This Row],[Order Date]])),DATE(VALUE(RIGHT(SalesData[[#This Row],[Order Date]],4)),VALUE(LEFT(SalesData[[#This Row],[Order Date]],FIND("/",SalesData[[#This Row],[Order Date]])-1)),VALUE(MID(SalesData[[#This Row],[Order Date]],FIND("/",SalesData[[#This Row],[Order Date]])+1,FIND("/",SalesData[[#This Row],[Order Date]],FIND("/",SalesData[[#This Row],[Order Date]])+1)-FIND("/",SalesData[[#This Row],[Order Date]])-1)))) -> 42682
A4: 3 | B4: CA-2016-138688 | C4: 42710 | D4: 6/16/2016 | E4: Second Class | F4: DV-13045 | G4: Darrin Van Huff | H4: Corporate | I4: United States | J4: Los Angeles | K4: California | L4: 90036 | M4: West | N4: OFF-LA-10000240 | O4: Office Supplies | P4: Labels | Q4: Self-Adhesive Address Labels for Typewriters by Universal | R4: 14.62 | S4: 2 | T4: 0 | U4: 6.8714 | V4: =IF(ISNUMBER(SalesData[[#This Row],[Order Date]]),DATE(YEAR(SalesData[[#This Row],[Order Date]]),DAY(SalesData[[#This Row],[Order Date]]),MONTH(SalesData[[#This Row],[Order Date]])),DATE(VALUE(RIGHT(SalesData[[#This Row],[Order Date]],4)),VALUE(LEFT(SalesData[[#This Row],[Order Date]],FIND("/",SalesData[[#This Row],[Order Date]])-1)),VALUE(MID(SalesData[[#This Row],[Order Date]],FIND("/",SalesData[[#This Row],[Order Date]])+1,FIND("/",SalesData[[#This Row],[Order Date]],FIND("/",SalesData[[#This Row],[Order Date]])+1)-FIND("/",SalesData[[#This Row],[Order Date]])-1)))) -> 42533
A5: 4 | B5: US-2015-108966 | C5: 42318 | D5: 10/18/2015 | E5: Standard Class | F5: SO-20335 | G5: Sean O'Donnell | H5: Consumer | I5: United States | J5: Fort Lauderdale | K5: Florida | L5: 33311 | M5: South | N5: FUR-TA-10000577 | O5: Furniture | P5: Tables | Q5: Bretford CR4500 Series Slim Rectangular Table | R5: 957.5775 | S5: 5 | T5: 0.45 | U5: -383.031 | V5: =IF(ISNUMBER(SalesData[[#This Row],[Order Date]]),DATE(YEAR(SalesData[[#This Row],[Order Date]]),DAY(SalesData[[#This Row],[Order Date]]),MONTH(SalesData[[#This Row],[Order Date]])),DATE(VALUE(RIGHT(SalesData[[#This Row],[Order Date]],4)),VALUE(LEFT(SalesData[[#This Row],[Order Date]],FIND("/",SalesData[[#This Row],[Order Date]])-1)),VALUE(MID(SalesData[[#This Row],[Order Date]],FIND("/",SalesData[[#This Row],[Order Date]])+1,FIND("/",SalesData[[#This Row],[Order Date]],FIND("/",SalesData[[#This Row],[Order Date]])+1)-FIND("/",SalesData[[#This Row],[Order Date]])-1)))) -> 42288
A6: 5 | B6: US-2015-108966 | C6: 42318 | D6: 10/18/2015 | E6: Standard Class | F6: SO-20335 | G6: Sean O'Donnell | H6: Consumer | I6: United States | J6: Fort Lauderdale | K6: Florida | L6: 33311 | M6: South | N6: OFF-ST-10000760 | O6: Office Supplies | P6: Storage | Q6: Eldon Fold 'N Roll Cart System | R6: 22.368 | S6: 2 | T6: 0.2 | U6: 2.5164 | V6: =IF(ISNUMBER(SalesData[[#This Row],[Order Date]]),DATE(YEAR(SalesData[[#This Row],[Order Date]]),DAY(SalesData[[#This Row],[Order Date]]),MONTH(SalesData[[#This Row],[Order Date]])),DATE(VALUE(RIGHT(SalesData[[#This Row],[Order Date]],4)),VALUE(LEFT(SalesData[[#This Row],[Order Date]],FIND("/",SalesData[[#This Row],[Order Date]])-1)),VALUE(MID(SalesData[[#This Row],[Order Date]],FIND("/",SalesData[[#This Row],[Order Date]])+1,FIND("/",SalesData[[#This Row],[Order Date]],FIND("/",SalesData[[#This Row],[Order Date]])+1)-FIND("/",SalesData[[#This Row],[Order Date]])-1)))) -> 42288
A7: 6 | B7: CA-2014-115812 | C7: 41888 | D7: 6/14/2014 | E7: Standard Class | F7: BH-11710 | G7: Brosina Hoffman | H7: Consumer | I7: United States | J7: Los Angeles | K7: California | L7: 90032 | M7: West | N7: FUR-FU-10001487 | O7: Furniture | P7: Furnishings | Q7: Eldon Expressions Wood and Plastic Desk Accessories, Cherry Wood | R7: 48.86 | S7: 7 | T7: 0 | U7: 14.1694 | V7: =IF(ISNUMBER(SalesData[[#This Row],[Order Date]]),DATE(YEAR(SalesData[[#This Row],[Order Date]]),DAY(SalesData[[#This Row],[Order Date]]),MONTH(SalesData[[#This Row],[Order Date]])),DATE(VALUE(RIGHT(SalesData[[#This Row],[Order Date]],4)),VALUE(LEFT(SalesData[[#This Row],[Order Date]],FIND("/",SalesData[[#This Row],[Order Date]])-1)),VALUE(MID(SalesData[[#This Row],[Order Date]],FIND("/",SalesData[[#This Row],[Order Date]])+1,FIND("/",SalesData[[#This Row],[Order Date]],FIND("/",SalesData[[#This Row],[Order Date]])+1)-FIND("/",SalesData[[#This Row],[Order Date]])-1)))) -> 41799
A8: 7 | B8: CA-2014-115812 | C8: 41888 | D8: 6/14/2014 | E8: Standard Class | F8: BH-11710 | G8: Brosina Hoffman | H8: Consumer | I8: United States | J8: Los Angeles | K8: California | L8: 90032 | M8: West | N8: OFF-AR-10002833 | O8: Office Supplies | P8: Art | Q8: Newell 322 | R8: 7.28 | S8: 4 | T8: 0 | U8: 1.9656 | V8: =IF(ISNUMBER(SalesData[[#This Row],[Order Date]]),DATE(YEAR(SalesData[[#This Row],[Order Date]]),DAY(SalesData[[#This Row],[Order Date]]),MONTH(SalesData[[#This Row],[Order Date]])),DATE(VALUE(RIGHT(SalesData[[#This Row],[Order Date]],4)),VALUE(LEFT(SalesData[[#This Row],[Order Date]],FIND("/",SalesData[[#This Row],[Order Date]])-1)),VALUE(MID(SalesData[[#This Row],[Order Date]],FIND("/",SalesData[[#This Row],[Order Date]])+1,FIND("/",SalesData[[#This Row],[Order Date]],FIND("/",SalesData[[#This Row],[Order Date]])+1)-FIND("/",SalesData[[#This Row],[Order Date]])-1)))) -> 41799
A9: 8 | B9: CA-2014-115812 | C9: 41888 | D9: 6/14/2014 | E9: Standard Class | F9: BH-11710 | G9: Brosina Hoffman | H9: Consumer | I9: United States | J9: Los Angeles | K9: California | L9: 90032 | M9: West | N9: TEC-PH-10002275 | O9: Technology | P9: Phones | Q9: Mitel 5320 IP Phone VoIP phone | R9: 907.152 | S9: 6 | T9: 0.2 | U9: 90.7152 | V9: =IF(ISNUMBER(SalesData[[#This Row],[Order Date]]),DATE(YEAR(SalesData[[#This Row],[Order Date]]),DAY(SalesData[[#This Row],[Order Date]]),MONTH(SalesData[[#This Row],[Order Date]])),DATE(VALUE(RIGHT(SalesData[[#This Row],[Order Date]],4)),VALUE(LEFT(SalesData[[#This Row],[Order Date]],FIND("/",SalesData[[#This Row],[Order Date]])-1)),VALUE(MID(SalesData[[#This Row],[Order Date]],FIND("/",SalesData[[#This Row],[Order Date]])+1,FIND("/",SalesData[[#This Row],[Order Date]],FIND("/",SalesData[[#This Row],[Order Date]])+1)-FIND("/",SalesData[[#This Row],[Order Date]])-1)))) -> 41799
A10: 9 | B10: CA-2014-115812 | C10: 41888 | D10: 6/14/2014 | E10: Standard Class | F10: BH-11710 | G10: Brosina Hoffman | H10: Consumer | I10: United States | J10: Los Angeles | K10: California | L10: 90032 | M10: West | N10: OFF-BI-10003910 | O10: Office Supplies | P10: Binders | Q10: DXL Angle-View Binders with Locking Rings by Samsill | R10: 18.504 | S10: 3 | T10: 0.2 | U10: 5.7825 | V10: =IF(ISNUMBER(SalesData[[#This Row],[Order Date]]),DATE(YEAR(SalesData[[#This Row],[Order Date]]),DAY(SalesData[[#This Row],[Order Date]]),MONTH(SalesData[[#This Row],[Order Date]])),DATE(VALUE(RIGHT(SalesData[[#This Row],[Order Date]],4)),VALUE(LEFT(SalesData[[#This Row],[Order Date]],FIND("/",SalesData[[#This Row],[Order Date]])-1)),VALUE(MID(SalesData[[#This Row],[Order Date]],FIND("/",SalesData[[#This Row],[Order Date]])+1,FIND("/",SalesData[[#This Row],[Order Date]],FIND("/",SalesData[[#This Row],[Order Date]])+1)-FIND("/",SalesData[[#This Row],[Order Date]])-1)))) -> 41799
A11: 10 | B11: CA-2014-115812 | C11: 41888 | D11: 6/14/2014 | E11: Standard Class | F11: BH-11710 | G11: Brosina Hoffman | H11: Consumer | I11: United States | J11: Los Angeles | K11: California | L11: 90032 | M11: West | N11: OFF-AP-10002892 | O11: Office Supplies | P11: Appliances | Q11: Belkin F5C206VTEL 6 Outlet Surge | R11: 114.9 | S11: 5 | T11: 0 | U11: 34.47 | V11: =IF(ISNUMBER(SalesData[[#This Row],[Order Date]]),DATE(YEAR(SalesData[[#This Row],[Order Date]]),DAY(SalesData[[#This Row],[Order Date]]),MONTH(SalesData[[#This Row],[Order Date]])),DATE(VALUE(RIGHT(SalesData[[#This Row],[Order Date]],4)),VALUE(LEFT(SalesData[[#This Row],[Order Date]],FIND("/",SalesData[[#This Row],[Order Date]])-1)),VALUE(MID(SalesData[[#This Row],[Order Date]],FIND("/",SalesData[[#This Row],[Order Date]])+1,FIND("/",SalesData[[#This Row],[Order Date]],FIND("/",SalesData[[#This Row],[Order Date]])+1)-FIND("/",SalesData[[#This Row],[Order Date]])-1)))) -> 41799
A12: 11 | B12: CA-2014-115812 | C12: 41888 | D12: 6/14/2014 | E12: Standard Class | F12: BH-11710 | G12: Brosina Hoffman | H12: Consumer | I12: United States | J12: Los Angeles | K12: California | L12: 90032 | M12: West | N12: FUR-TA-10001539 | O12: Furniture | P12: Tables | Q12: Chromcraft Rectangular Conference Tables | R12: 1706.184 | S12: 9 | T12: 0.2 | U12: 85.3092 | V12: =IF(ISNUMBER(SalesData[[#This Row],[Order Date]]),DATE(YEAR(SalesData[[#This Row],[Order Date]]),DAY(SalesData[[#This Row],[Order Date]]),MONTH(SalesData[[#This Row],[Order Date]])),DATE(VALUE(RIGHT(SalesData[[#This Row],[Order Date]],4)),VALUE(LEFT(SalesData[[#This Row],[Order Date]],FIND("/",SalesData[[#This Row],[Order Date]])-1)),VALUE(MID(SalesData[[#This Row],[Order Date]],FIND("/",SalesData[[#This Row],[Order Date]])+1,FIND("/",SalesData[[#This Row],[Order Date]],FIND("/",SalesData[[#This Row],[Order Date]])+1)-FIND("/",SalesData[[#This Row],[Order Date]])-1)))) -> 41799
A13: 12 | B13: CA-2014-115812 | C13: 41888 | D13: 6/14/2014 | E13: Standard Class | F13: BH-11710 | G13: Brosina Hoffman | H13: Consumer | I13: United States | J13: Los Angeles | K13: California | L13: 90032 | M13: West | N13: TEC-PH-10002033 | O13: Technology | P13: Phones | Q13: Konftel 250 Conference phone - Charcoal black | R13: 911.424 | S13: 4 | T13: 0.2 | U13: 68.3568 | V13: =IF(ISNUMBER(SalesData[[#This Row],[Order Date]]),DATE(YEAR(SalesData[[#This Row],[Order Date]]),DAY(SalesData[[#This Row],[Order Date]]),MONTH(SalesData[[#This Row],[Order Date]])),DATE(VALUE(RIGHT(SalesData[[#This Row],[Order Date]],4)),VALUE(LEFT(SalesData[[#This Row],[Order Date]],FIND("/",SalesData[[#This Row],[Order Date]])-1)),VALUE(MID(SalesData[[#This Row],[Order Date]],FIND("/",SalesData[[#This Row],[Order Date]])+1,FIND("/",SalesData[[#This Row],[Order Date]],FIND("/",SalesData[[#This Row],[Order Date]])+1)-FIND("/",SalesData[[#This Row],[Order Date]])-1)))) -> 41799
A14: 13 | B14: CA-2017-114412 | C14: 4/15/2017 | D14: 4/20/2017 | E14: Standard Class | F14: AA-10480 | G14: Andrew Allen | H14: Consumer | I14: United States | J14: Concord | K14: North Carolina | L14: 28027 | M14: South | N14: OFF-PA-10002365 | O14: Office Supplies | P14: Paper | Q14: Xerox 1967 | R14: 15.552 | S14: 3 | T14: 0.2 | U14: 5.4432 | V14: =IF(ISNUMBER(SalesData[[#This Row],[Order Date]]),DATE(YEAR(SalesData[[#This Row],[Order Date]]),DAY(SalesData[[#This Row],[Order Date]]),MONTH(SalesData[[#This Row],[Order Date]])),DATE(VALUE(RIGHT(SalesData[[#This Row],[Order Date]],4)),VALUE(LEFT(SalesData[[#This Row],[Order Date]],FIND("/",SalesData[[#This Row],[Order Date]])-1)),VALUE(MID(SalesData[[#This Row],[Order Date]],FIND("/",SalesData[[#This Row],[Order Date]])+1,FIND("/",SalesData[[#This Row],[Order Date]],FIND("/",SalesData[[#This Row],[Order Date]])+1)-FIND("/",SalesData[[#This Row],[Order Date]])-1)))) -> 42840
A15: 14 | B15: CA-2016-161389 | C15: 42502 | D15: 42655 | E15: Standard Class | F15: IM-15070 | G15: Irene Maddox | H15: Consumer | I15: United States | J15: Seattle | K15: Washington | L15: 98103 | M15: West | N15: OFF-BI-10003656 | O15: Office Supplies | P15: Binders | Q15: Fellowes PB200 Plastic Comb Binding Machine | R15: 407.976 | S15: 3 | T15: 0.2 | U15: 132.5922 | V15: =IF(ISNUMBER(SalesData[[#This Row],[Order Date]]),DATE(YEAR(SalesData[[#This Row],[Order Date]]),DAY(SalesData[[#This Row],[Order Date]]),MONTH(SalesData[[#This Row],[Order Date]])),DATE(VALUE(RIGHT(SalesData[[#This Row],[Order Date]],4)),VALUE(LEFT(SalesData[[#This Row],[Order Date]],FIND("/",SalesData[[#This Row],[Order Date]])-1)),VALUE(MID(SalesData[[#This Row],[Order Date]],FIND("/",SalesData[[#This Row],[Order Date]])+1,FIND("/",SalesData[[#This Row],[Order Date]],FIND("/",SalesData[[#This Row],[Order Date]])+1)-FIND("/",SalesData[[#This Row],[Order Date]])-1)))) -> 42709
A16: 15 | B16: US-2015-118983 | C16: 11/22/2015 | D16: 11/26/2015 | E16: Standard Class | F16: HP-14815 | G16: Harold Pawlan | H16: Home Office | I16: United States | J16: Fort Worth | K16: Texas | L16: 76106 | M16: Central | N16: OFF-AP-10002311 | O16: Office Supplies | P16: Appliances | Q16: Holmes Replacement Filter for HEPA Air Cleaner, Very Large Room, HEPA Filter | R16: 68.81 | S16: 5 | T16: 0.8 | U16: -123.858 | V16: =IF(ISNUMBER(SalesData[[#This Row],[Order Date]]),DATE(YEAR(SalesData[[#This Row],[Order Date]]),DAY(SalesData[[#This Row],[Order Date]]),MONTH(SalesData[[#This Row],[Order Date]])),DATE(VALUE(RIGHT(SalesData[[#This Row],[Order Date]],4)),VALUE(LEFT(SalesData[[#This Row],[Order Date]],FIND("/",SalesData[[#This Row],[Order Date]])-1)),VALUE(MID(SalesData[[#This Row],[Order Date]],FIND("/",SalesData[[#This Row],[Order Date]])+1,FIND("/",SalesData[[#This Row],[Order Date]],FIND("/",SalesData[[#This Row],[Order Date]])+1)-FIND("/",SalesData[[#This Row],[Order Date]])-1)))) -> 42330
A17: 16 | B17: US-2015-118983 | C17: 11/22/2015 | D17: 11/26/2015 | E17: Standard Class | F17: HP-14815 | G17: Harold Pawlan | H17: Home Office | I17: United States | J17: Fort Worth | K17: Texas | L17: 76106 | M17: Central | N17: OFF-BI-10000756 | O17: Office Supplies | P17: Binders | Q17: Storex DuraTech Recycled Plastic Frosted Binders | R17: 2.544 | S17: 3 | T17: 0.8 | U17: -3.816 | V17: =IF(ISNUMBER(SalesData[[#This Row],[Order Date]]),DATE(YEAR(SalesData[[#This Row],[Order Date]]),DAY(SalesData[[#This Row],[Order Date]]),MONTH(SalesData[[#This Row],[Order Date]])),DATE(VALUE(RIGHT(SalesData[[#This Row],[Order Date]],4)),VALUE(LEFT(SalesData[[#This Row],[Order Date]],FIND("/",SalesData[[#This Row],[Order Date]])-1)),VALUE(MID(SalesData[[#This Row],[Order Date]],FIND("/",SalesData[[#This Row],[Order Date]])+1,FIND("/",SalesData[[#This Row],[Order Date]],FIND("/",SalesData[[#This Row],[Order Date]])+1)-FIND("/",SalesData[[#This Row],[Order Date]])-1)))) -> 42330
A18: 17 | B18: CA-2014-105893 | C18: 41954 | D18: 11/18/2014 | E18: Standard Class | F18: PK-19075 | G18: Pete Kriz | H18: Consumer | I18: United States | J18: Madison | K18: Wisconsin | L18: 53711 | M18: Central | N18: OFF-ST-10004186 | O18: Office Supplies | P18: Storage | Q18: Stur-D-Stor Shelving, Vertical 5-Shelf: 72"H x 36"W x 18 1/2"D | R18: 665.88 | S18: 6 | T18: 0 | U18: 13.3176 | V18: =IF(ISNUMBER(SalesData[[#This Row],[Order Date]]),DATE(YEAR(SalesData[[#This Row],[Order Date]]),DAY(SalesData[[#This Row],[Order Date]]),MONTH(SalesData[[#This Row],[Order Date]])),DATE(VALUE(RIGHT(SalesData[[#This Row],[Order Date]],4)),VALUE(LEFT(SalesData[[#This Row],[Order Date]],FIND("/",SalesData[[#This Row],[Order Date]])-1)),VALUE(MID(SalesData[[#This Row],[Order Date]],FIND("/",SalesData[[#This Row],[Order Date]])+1,FIND("/",SalesData[[#This Row],[Order Date]],FIND("/",SalesData[[#This Row],[Order Date]])+1)-FIND("/",SalesData[[#This Row],[Order Date]])-1)))) -> 41954
A19: 18 | B19: CA-2014-167164 | C19: 5/13/2014 | D19: 5/15/2014 | E19: Second Class | F19: AG-10270 | G19: Alejandro Grove | H19: Consumer | I19: United States | J19: West Jordan | K19: Utah | L19: 84084 | M19: West | N19: OFF-ST-10000107 | O19: Office Supplies | P19: Storage | Q19: Fellowes Super Stor/Drawer | R19: 55.5 | S19: 2 | T19: 0 | U19: 9.99 | V19: =IF(ISNUMBER(SalesData[[#This Row],[Order Date]]),DATE(YEAR(SalesData[[#This Row],[Order Date]]),DAY(SalesData[[#This Row],[Order Date]]),MONTH(SalesData[[#This Row],[Order Date]])),DATE(VALUE(RIGHT(SalesData[[#This Row],[Order Date]],4)),VALUE(LEFT(SalesData[[#This Row],[Order Date]],FIND("/",SalesData[[#This Row],[Order Date]])-1)),VALUE(MID(SalesData[[#This Row],[Order Date]],FIND("/",SalesData[[#This Row],[Order Date]])+1,FIND("/",SalesData[[#This Row],[Order Date]],FIND("/",SalesData[[#This Row],[Order Date]])+1)-FIND("/",SalesData[[#This Row],[Order Date]])-1)))) -> 41772
A20: 19 | B20: CA-2014-143336 | C20: 8/27/2014 | D20: 41648 | E20: Second Class | F20: ZD-21925 | G20: Zuschuss Donatelli | H20: Consumer | I20: United States | J20: San Francisco | K20: California | L20: 94109 | M20: West | N20: OFF-AR-10003056 | O20: Office Supplies | P20: Art | Q20: Newell 341 | R20: 8.56 | S20: 2 | T20: 0 | U20: 2.4824 | V20: =IF(ISNUMBER(SalesData[[#This Row],[Order Date]]),DATE(YEAR(SalesData[[#This Row],[Order Date]]),DAY(SalesData[[#This Row],[Order Date]]),MONTH(SalesData[[#This Row],[Order Date]])),DATE(VALUE(RIGHT(SalesData[[#This Row],[Order Date]],4)),VALUE(LEFT(SalesData[[#This Row],[Order Date]],FIND("/",SalesData[[#This Row],[Order Date]])-1)),VALUE(MID(SalesData[[#This Row],[Order Date]],FIND("/",SalesData[[#This Row],[Order Date]])+1,FIND("/",SalesData[[#This Row],[Order Date]],FIND("/",SalesData[[#This Row],[Order Date]])+1)-FIND("/",SalesData[[#This Row],[Order Date]])-1)))) -> 41878
A21: 20 | B21: CA-2014-143336 | C21: 8/27/2014 | D21: 41648 | E21: Second Class | F21: ZD-21925 | G21: Zuschuss Donatelli | H21: Consumer | I21: United States | J21: San Francisco | K21: California | L21: 94109 | M21: West | N21: TEC-PH-10001949 | O21: Technology | P21: Phones | Q21: Cisco SPA 501G IP Phone | R21: 213.48 | S21: 3 | T21: 0.2 | U21: 16.011 | V21: =IF(ISNUMBER(SalesData[[#This Row],[Order Date]]),DATE(YEAR(SalesData[[#This Row],[Order Date]]),DAY(SalesData[[#This Row],[Order Date]]),MONTH(SalesData[[#This Row],[Order Date]])),DATE(VALUE(RIGHT(SalesData[[#This Row],[Order Date]],4)),VALUE(LEFT(SalesData[[#This Row],[Order Date]],FIND("/",SalesData[[#This Row],[Order Date]])-1)),VALUE(MID(SalesData[[#This Row],[Order Date]],FIND("/",SalesData[[#This Row],[Order Date]])+1,FIND("/",SalesData[[#This Row],[Order Date]],FIND("/",SalesData[[#This Row],[Order Date]])+1)-FIND("/",SalesData[[#This Row],[Order Date]])-1)))) -> 41878
A22: 21 | B22: CA-2014-143336 | C22: 8/27/2014 | D22: 41648 | E22: Second Class | F22: ZD-21925 | G22: Zuschuss Donatelli | H22: Consumer | I22: United States | J22: San Francisco | K22: California | L22: 94109 | M22: West | N22: OFF-BI-10002215 | O22: Office Supplies | P22: Binders | Q22: Wilson Jones Hanging View Binder, White, 1" | R22: 22.72 | S22: 4 | T22: 0.2 | U22: 7.384 | V22: =IF(ISNUMBER(SalesData[[#This Row],[Order Date]]),DATE(YEAR(SalesData[[#This Row],[Order Date]]),DAY(SalesData[[#This Row],[Order Date]]),MONTH(SalesData[[#This Row],[Order Date]])),DATE(VALUE(RIGHT(SalesData[[#This Row],[Order Date]],4)),VALUE(LEFT(SalesData[[#This Row],[Order Date]],FIND("/",SalesData[[#This Row],[Order Date]])-1)),VALUE(MID(SalesData[[#This Row],[Order Date]],FIND("/",SalesData[[#This Row],[Order Date]])+1,FIND("/",SalesData[[#This Row],[Order Date]],FIND("/",SalesData[[#This Row],[Order Date]])+1)-FIND("/",SalesData[[#This Row],[Order Date]])-1)))) -> 41878
A23: 22 | B23: CA-2016-137330 | C23: 42625 | D23: 12/13/2016 | E23: Standard Class | F23: KB-16585 | G23: Ken Black | H23: Corporate | I23: United States | J23: Fremont | K23: Nebraska | L23: 68025 | M23: Central | N23: OFF-AR-10000246 | O23: Office Supplies | P23: Art | Q23: Newell 318 | R23: 19.46 | S23: 7 | T23: 0 | U23: 5.0596 | V23: =IF(ISNUMBER(SalesData[[#This Row],[Order Date]]),DATE(YEAR(SalesData[[#This Row],[Order Date]]),DAY(SalesData[[#This Row],[Order Date]]),MONTH(SalesData[[#This Row],[Order Date]])),DATE(VALUE(RIGHT(SalesData[[#This Row],[Order Date]],4)),VALUE(LEFT(SalesData[[#This Row],[Order Date]],FIND("/",SalesData[[#This Row],[Order Date]])-1)),VALUE(MID(SalesData[[#This Row],[Order Date]],FIND("/",SalesData[[#This Row],[Order Date]])+1,FIND("/",SalesData[[#This Row],[Order Date]],FIND("/",SalesData[[#This Row],[Order Date]])+1)-FIND("/",SalesData[[#This Row],[Order Date]])-1)))) -> 42713
A24: 23 | B24: CA-2016-137330 | C24: 42625 | D24: 12/13/2016 | E24: Standard Class | F24: KB-16585 | G24: Ken Black | H24: Corporate | I24: United States | J24: Fremont | K24: Nebraska | L24: 68025 | M24: Central | N24: OFF-AP-10001492 | O24: Office Supplies | P24: Appliances | Q24: Acco Six-Outlet Power Strip, 4' Cord Length | R24: 60.34 | S24: 7 | T24: 0 | U24: 15.6884 | V24: =IF(ISNUMBER(SalesData[[#This Row],[Order Date]]),DATE(YEAR(SalesData[[#This Row],[Order Date]]),DAY(SalesData[[#This Row],[Order Date]]),MONTH(SalesData[[#This Row],[Order Date]])),DATE(VALUE(RIGHT(SalesData[[#This Row],[Order Date]],4)),VALUE(LEFT(SalesData[[#This Row],[Order Date]],FIND("/",SalesData[[#This Row],[Order Date]])-1)),VALUE(MID(SalesData[[#This Row],[Order Date]],FIND("/",SalesData[[#This Row],[Order Date]])+1,FIND("/",SalesData[[#This Row],[Order Date]],FIND("/",SalesData[[#This Row],[Order Date]])+1)-FIND("/",SalesData[[#This Row],[Order Date]])-1)))) -> 42713
A25: 24 | B25: US-2017-156909 | C25: 7/16/2017 | D25: 7/18/2017 | E25: Second Class | F25: SF-20065 | G25: Sandra Flanagan | H25: Consumer | I25: United States | J25: Philadelphia | K25: Pennsylvania | L25: 19140 | M25: East | N25: FUR-CH-10002774 | O25: Furniture | P25: Chairs | Q25: Global Deluxe Stacking Chair, Gray | R25: 71.372 | S25: 2 | T25: 0.3 | U25: -1.0196 | V25: =IF(ISNUMBER(SalesData[[#This Row],[Order Date]]),DATE(YEAR(SalesData[[#This Row],[Order Date]]),DAY(SalesData[[#This Row],[Order Date]]),MONTH(SalesData[[#This Row],[Order Date]])),DATE(VALUE(RIGHT(SalesData[[#This Row],[Order Date]],4)),VALUE(LEFT(SalesData[[#This Row],[Order Date]],FIND("/",SalesData[[#This Row],[Order Date]])-1)),VALUE(MID(SalesData[[#This Row],[Order Date]],FIND("/",SalesData[[#This Row],[Order Date]])+1,FIND("/",SalesData[[#This Row],[Order Date]],FIND("/",SalesData[[#This Row],[Order Date]])+1)-FIND("/",SalesData[[#This Row],[Order Date]])-1)))) -> 42932
A26: 25 | B26: CA-2015-106320 | C26: 9/25/2015 | D26: 9/30/2015 | E26: Standard Class | F26: EB-13870 | G26: Emily Burns | H26: Consumer | I26: United States | J26: Orem | K26: Utah | L26: 84057 | M26: West | N26: FUR-TA-10000577 | O26: Furniture | P26: Tables | Q26: Bretford CR4500 Series Slim Rectangular Table | R26: 1044.63 | S26: 3 | T26: 0 | U26: 240.2649 | V26: =IF(ISNUMBER(SalesData[[#This Row],[Order Date]]),DATE(YEAR(SalesData[[#This Row],[Order Date]]),DAY(SalesData[[#This Row],[Order Date]]),MONTH(SalesData[[#This Row],[Order Date]])),DATE(VALUE(RIGHT(SalesData[[#This Row],[Order Date]],4)),VALUE(LEFT(SalesData[[#This Row],[Order Date]],FIND("/",SalesData[[#This Row],[Order Date]])-1)),VALUE(MID(SalesData[[#This Row],[Order Date]],FIND("/",SalesData[[#This Row],[Order Date]])+1,FIND("/",SalesData[[#This Row],[Order Date]],FIND("/",SalesData[[#This Row],[Order Date]])+1)-FIND("/",SalesData[[#This Row],[Order Date]])-1)))) -> 42272
A27: 26 | B27: CA-2016-121755 | C27: 1/16/2016 | D27: 1/20/2016 | E27: Second Class | F27: EH-13945 | G27: Eric Hoffmann | H27: Consumer | I27: United States | J27: Los Angeles | K27: California | L27: 90049 | M27: West | N27: OFF-BI-10001634 | O27: Office Supplies | P27: Binders | Q27: Wilson Jones Active Use Binders | R27: 11.648 | S27: 2 | T27: 0.2 | U27: 4.2224 | V27: =IF(ISNUMBER(SalesData[[#This Row],[Order Date]]),DATE(YEAR(SalesData[[#This Row],[Order Date]]),DAY(SalesData[[#This Row],[Order Date]]),MONTH(SalesData[[#This Row],[Order Date]])),DATE(VALUE(RIGHT(SalesData[[#This Row],[Order Date]],4)),VALUE(LEFT(SalesData[[#This Row],[Order Date]],FIND("/",SalesData[[#This Row],[Order Date]])-1)),VALUE(MID(SalesData[[#This Row],[Order Date]],FIND("/",SalesData[[#This Row],[Order Date]])+1,FIND("/",SalesData[[#This Row],[Order Date]],FIND("/",SalesData[[#This Row],[Order Date]])+1)-FIND("/",SalesData[[#This Row],[Order Date]])-1)))) -> 42385
A28: 27 | B28: CA-2016-121755 | C28: 1/16/2016 | D28: 1/20/2016 | E28: Second Class | F28: EH-13945 | G28: Eric Hoffmann | H28: Consumer | I28: United States | J28: Los Angeles | K28: California | L28: 90049 | M28: West | N28: TEC-AC-10003027 | O28: Technology | P28: Accessories | Q28: Imation 8GB Mini TravelDrive USB 2.0 Flash Drive | R28: 90.57 | S28: 3 | T28: 0 | U28: 11.7741 | V28: =IF(ISNUMBER(SalesData[[#This Row],[Order Date]]),DATE(YEAR(SalesData[[#This Row],[Order Date]]),DAY(SalesData[[#This Row],[Order Date]]),MONTH(SalesData[[#This Row],[Order Date]])),DATE(VALUE(RIGHT(SalesData[[#This Row],[Order Date]],4)),VALUE(LEFT(SalesData[[#This Row],[Order Date]],FIND("/",SalesData[[#This Row],[Order Date]])-1)),VALUE(MID(SalesData[[#This Row],[Order Date]],FIND("/",SalesData[[#This Row],[Order Date]])+1,FIND("/",SalesData[[#This Row],[Order Date]],FIND("/",SalesData[[#This Row],[Order Date]])+1)-FIND("/",SalesData[[#This Row],[Order Date]])-1)))) -> 42385
A29: 28 | B29: US-2015-150630 | C29: 9/17/2015 | D29: 9/21/2015 | E29: Standard Class | F29: TB-21520 | G29: Tracy Blumstein | H29: Consumer | I29: United States | J29: Philadelphia | K29: Pennsylvania | L29: 19140 | M29: East | N29: FUR-BO-10004834 | O29: Furniture | P29: Bookcases | Q29: Riverside Palais Royal Lawyers Bookcase, Royale Cherry Finish | R29: 3083.43 | S29: 7 | T29: 0.5 | U29: -1665.0522 | V29: =IF(ISNUMBER(SalesData[[#This Row],[Order Date]]),DATE(YEAR(SalesData[[#This Row],[Order Date]]),DAY(SalesData[[#This Row],[Order Date]]),MONTH(SalesData[[#This Row],[Order Date]])),DATE(VALUE(RIGHT(SalesData[[#This Row],[Order Date]],4)),VALUE(LEFT(SalesData[[#This Row],[Order Date]],FIND("/",SalesData[[#This Row],[Order Date]])-1)),VALUE(MID(SalesData[[#This Row],[Order Date]],FIND("/",SalesData[[#This Row],[Order Date]])+1,FIND("/",SalesData[[#This Row],[Order Date]],FIND("/",SalesData[[#This Row],[Order Date]])+1)-FIND("/",SalesData[[#This Row],[Order Date]])-1)))) -> 42264
A30: 29 | B30: US-2015-150630 | C30: 9/17/2015 | D30: 9/21/2015 | E30: Standard Class | F30: TB-21520 | G30: Tracy Blumstein | H30: Consumer | I30: United States | J30: Philadelphia | K30: Pennsylvania | L30: 19140 | M30: East | N30: OFF-BI-10000474 | O30: Office Supplies | P30: Binders | Q30: Avery Recycled Flexi-View Covers for Binding Systems | R30: 9.618 | S30: 2 | T30: 0.7 | U30: -7.0532 | V30: =IF(ISNUMBER(SalesData[[#This Row],[Order Date]]),DATE(YEAR(SalesData[[#This Row],[Order Date]]),DAY(SalesData[[#This Row],[Order Date]]),MONTH(SalesData[[#This Row],[Order Date]])),DATE(VALUE(RIGHT(SalesData[[#This Row],[Order Date]],4)),VALUE(LEFT(SalesData[[#This Row],[Order Date]],FIND("/",SalesData[[#This Row],[Order Date]])-1)),VALUE(MID(SalesData[[#This Row],[Order Date]],FIND("/",SalesData[[#This Row],[Order Date]])+1,FIND("/",SalesData[[#This Row],[Order Date]],FIND("/",SalesData[[#This Row],[Order Date]])+1)-FIND("/",SalesData[[#This Row],[Order Date]])-1)))) -> 42264
A31: 30 | B31: US-2015-150630 | C31: 9/17/2015 | D31: 9/21/2015 | E31: Standard Class | F31: TB-21520 | G31: Tracy Blumstein | H31: Consumer | I31: United States | J31: Philadelphia | K31: Pennsylvania | L31: 19140 | M31: East | N31: FUR-FU-10004848 | O31: Furniture | P31: Furnishings | Q31: Howard Miller 13-3/4" Diameter Brushed Chrome Round Wall Clock | R31: 124.2 | S31: 3 | T31: 0.2 | U31: 15.525 | V31: =IF(ISNUMBER(SalesData[[#This Row],[Order Date]]),DATE(YEAR(SalesData[[#This Row],[Order Date]]),DAY(SalesData[[#This Row],[Order Date]]),MONTH(SalesData[[#This Row],[Order Date]])),DATE(VALUE(RIGHT(SalesData[[#This Row],[Order Date]],4)),VALUE(LEFT(SalesData[[#This Row],[Order Date]],FIND("/",SalesData[[#This Row],[Order Date]])-1)),VALUE(MID(SalesData[[#This Row],[Order Date]],FIND("/",SalesData[[#This Row],[Order Date]])+1,FIND("/",SalesData[[#This Row],[Order Date]],FIND("/",SalesData[[#This Row],[Order Date]])+1)-FIND("/",SalesData[[#This Row],[Order Date]])-1)))) -> 42264
A32: 31 | B32: US-2015-150630 | C32: 9/17/2015 | D32: 9/21/2015 | E32: Standard Class | F32: TB-21520 | G32: Tracy Blumstein | H32: Consumer | I32: United States | J32: Philadelphia | K32: Pennsylvania | L32: 19140 | M32: East | N32: OFF-EN-10001509 | O32: Office Supplies | P32: Envelopes | Q32: Poly String Tie Envelopes | R32: 3.264 | S32: 2 | T32: 0.2 | U32: 1.1016 | V32: =IF(ISNUMBER(SalesData[[#This Row],[Order Date]]),DATE(YEAR(SalesData[[#This Row],[Order Date]]),DAY(SalesData[[#This Row],[Order Date]]),MONTH(SalesData[[#This Row],[Order Date]])),DATE(VALUE(RIGHT(SalesData[[#This Row],[Order Date]],4)),VALUE(LEFT(SalesData[[#This Row],[Order Date]],FIND("/",SalesData[[#This Row],[Order Date]])-1)),VALUE(MID(SalesData[[#This Row],[Order Date]],FIND("/",SalesData[[#This Row],[Order Date]])+1,FIND("/",SalesData[[#This Row],[Order Date]],FIND("/",SalesData[[#This Row],[Order Date]])+1)-FIND("/",SalesData[[#This Row],[Order Date]])-1)))) -> 42264
A33: 32 | B33: US-2015-150630 | C33: 9/17/2015 | D33: 9/21/2015 | E33: Standard Class | F33: TB-21520 | G33: Tracy Blumstein | H33: Consumer | I33: United States | J33: Philadelphia | K33: Pennsylvania | L33: 19140 | M33: East | N33: OFF-AR-10004042 | O33: Office Supplies | P33: Art | Q33: BOSTON Model 1800 Electric Pencil Sharpeners, Putty/Woodgrain | R33: 86.304 | S33: 6 | T33: 0.2 | U33: 9.7092 | V33: =IF(ISNUMBER(SalesData[[#This Row],[Order Date]]),DATE(YEAR(SalesData[[#This Row],[Order Date]]),DAY(SalesData[[#This Row],[Order Date]]),MONTH(SalesData[[#This Row],[Order Date]])),DATE(VALUE(RIGHT(SalesData[[#This Row],[Order Date]],4)),VALUE(LEFT(SalesData[[#This Row],[Order Date]],FIND("/",SalesData[[#This Row],[Order Date]])-1)),VALUE(MID(SalesData[[#This Row],[Order Date]],FIND("/",SalesData[[#This Row],[Order Date]])+1,FIND("/",SalesData[[#This Row],[Order Date]],FIND("/",SalesData[[#This Row],[Order Date]])+1)-FIND("/",SalesData[[#This Row],[Order Date]])-1)))) -> 42264
A34: 33 | B34: US-2015-150630 | C34: 9/17/2015 | D34: 9/21/2015 | E34: Standard Class | F34: TB-21520 | G34: Tracy Blumstein | H34: Consumer | I34: United States | J34: Philadelphia | K34: Pennsylvania | L34: 19140 | M34: East | N34: OFF-BI-10001525 | O34: Office Supplies | P34: Binders | Q34: Acco Pressboard Covers with Storage Hooks, 14 7/8" x 11", Executive Red | R34: 6.858 | S34: 6 | T34: 0.7 | U34: -5.715 | V34: =IF(ISNUMBER(SalesData[[#This Row],[Order Date]]),DATE(YEAR(SalesData[[#This Row],[Order Date]]),DAY(SalesData[[#This Row],[Order Date]]),MONTH(SalesData[[#This Row],[Order Date]])),DATE(VALUE(RIGHT(SalesData[[#This Row],[Order Date]],4)),VALUE(LEFT(SalesData[[#This Row],[Order Date]],FIND("/",SalesData[[#This Row],[Order Date]])-1)),VALUE(MID(SalesData[[#This Row],[Order Date]],FIND("/",SalesData[[#This Row],[Order Date]])+1,FIND("/",SalesData[[#This Row],[Order Date]],FIND("/",SalesData[[#This Row],[Order Date]])+1)-FIND("/",SalesData[[#This Row],[Order Date]])-1)))) -> 42264
A35: 34 | B35: US-2015-150630 | C35: 9/17/2015 | D35: 9/21/2015 | E35: Standard Class | F35: TB-21520 | G35: Tracy Blumstein | H35: Consumer | I35: United States | J35: Philadelphia | K35: Pennsylvania | L35: 19140 | M35: East | N35: OFF-AR-10001683 | O35: Office Supplies | P35: Art | Q35: Lumber Crayons | R35: 15.76 | S35: 2 | T35: 0.2 | U35: 3.546 | V35: =IF(ISNUMBER(SalesData[[#This Row],[Order Date]]),DATE(YEAR(SalesData[[#This Row],[Order Date]]),DAY(SalesData[[#This Row],[Order Date]]),MONTH(SalesData[[#This Row],[Order Date]])),DATE(VALUE(RIGHT(SalesData[[#This Row],[Order Date]],4)),VALUE(LEFT(SalesData[[#This Row],[Order Date]],FIND("/",SalesData[[#This Row],[Order Date]])-1)),VALUE(MID(SalesData[[#This Row],[Order Date]],FIND("/",SalesData[[#This Row],[Order Date]])+1,FIND("/",SalesData[[#This Row],[Order Date]],FIND("/",SalesData[[#This Row],[Order Date]])+1)-FIND("/",SalesData[[#This Row],[Order Date]])-1)))) -> 42264
A36: 35 | B36: CA-2017-107727 | C36: 10/19/2017 | D36: 10/23/2017 | E36: Second Class | F36: MA-17560 | G36: Matt Abelman | H36: Home Office | I36: United States | J36: Houston | K36: Texas | L36: 77095 | M36: Central | N36: OFF-PA-10000249 | O36: Office Supplies | P36: Paper | Q36: Easy-staple paper | R36: 29.472 | S36: 3 | T36: 0.2 | U36: 9.9468 | V36: =IF(ISNUMBER(SalesData[[#This Row],[Order Date]]),DATE(YEAR(SalesData[[#This Row],[Order Date]]),DAY(SalesData[[#This Row],[Order Date]]),MONTH(SalesData[[#This Row],[Order Date]])),DATE(VALUE(RIGHT(SalesData[[#This Row],[Order Date]],4)),VALUE(LEFT(SalesData[[#This Row],[Order Date]],FIND("/",SalesData[[#This Row],[Order Date]])-1)),VALUE(MID(SalesData[[#This Row],[Order Date]],FIND("/",SalesData[[#This Row],[Order Date]])+1,FIND("/",SalesData[[#This Row],[Order Date]],FIND("/",SalesData[[#This Row],[Order Date]])+1)-FIND("/",SalesData[[#This Row],[Order Date]])-1)))) -> 43027
A37: 36 | B37: CA-2016-117590 | C37: 42594 | D37: 42655 | E37: First Class | F37: GH-14485 | G37: Gene Hale | H37: Corporate | I37: United States | J37: Richardson | K37: Texas | L37: 75080 | M37: Central | N37: TEC-PH-10004977 | O37: Technology | P37: Phones | Q37: GE 30524EE4 | R37: 1097.544 | S37: 7 | T37: 0.2 | U37: 123.4737 | V37: =IF(ISNUMBER(SalesData[[#This Row],[Order Date]]),DATE(YEAR(SalesData[[#This Row],[Order Date]]),DAY(SalesData[[#This Row],[Order Date]]),MONTH(SalesData[[#This Row],[Order Date]])),DATE(VALUE(RIGHT(SalesData[[#This Row],[Order Date]],4)),VALUE(LEFT(SalesData[[#This Row],[Order Date]],FIND("/",SalesData[[#This Row],[Order Date]])-1)),VALUE(MID(SalesData[[#This Row],[Order Date]],FIND("/",SalesData[[#This Row],[Order Date]])+1,FIND("/",SalesData[[#This Row],[Order Date]],FIND("/",SalesData[[#This Row],[Order Date]])+1)-FIND("/",SalesData[[#This Row],[Order Date]])-1)))) -> 42712
A38: 37 | B38: CA-2016-117590 | C38: 42594 | D38: 42655 | E38: First Class | F38: GH-14485 | G38: Gene Hale | H38: Corporate | I38: United States | J38: Richardson | K38: Texas | L38: 75080 | M38: Central | N38: FUR-FU-10003664 | O38: Furniture | P38: Furnishings | Q38: Electrix Architect's Clamp-On Swing Arm Lamp, Black | R38: 190.92 | S38: 5 | T38: 0.6 | U38: -147.963 | V38: =IF(ISNUMBER(SalesData[[#This Row],[Order Date]]),DATE(YEAR(SalesData[[#This Row],[Order Date]]),DAY(SalesData[[#This Row],[Order Date]]),MONTH(SalesData[[#This Row],[Order Date]])),DATE(VALUE(RIGHT(SalesData[[#This Row],[Order Date]],4)),VALUE(LEFT(SalesData[[#This Row],[Order Date]],FIND("/",SalesData[[#This Row],[Order Date]])-1)),VALUE(MID(SalesData[[#This Row],[Order Date]],FIND("/",SalesData[[#This Row],[Order Date]])+1,FIND("/",SalesData[[#This Row],[Order Date]],FIND("/",SalesData[[#This Row],[Order Date]])+1)-FIND("/",SalesData[[#This Row],[Order Date]])-1)))) -> 42712
A39: 38 | B39: CA-2015-117415 | C39: 12/27/2015 | D39: 12/31/2015 | E39: Standard Class | F39: SN-20710 | G39: Steve Nguyen | H39: Home Office | I39: United States | J39: Houston | K39: Texas | L39: 77041 | M39: Central | N39: OFF-EN-10002986 | O39: Office Supplies | P39: Envelopes | Q39: #10-4 1/8" x 9 1/2" Premium Diagonal Seam Envelopes | R39: 113.328 | S39: 9 | T39: 0.2 | U39: 35.415 | V39: =IF(ISNUMBER(SalesData[[#This Row],[Order Date]]),DATE(YEAR(SalesData[[#This Row],[Order Date]]),DAY(SalesData[[#This Row],[Order Date]]),MONTH(SalesData[[#This Row],[Order Date]])),DATE(VALUE(RIGHT(SalesData[[#This Row],[Order Date]],4)),VALUE(LEFT(SalesData[[#This Row],[Order Date]],FIND("/",SalesData[[#This Row],[Order Date]])-1)),VALUE(MID(SalesData[[#This Row],[Order Date]],FIND("/",SalesData[[#This Row],[Order Date]])+1,FIND("/",SalesData[[#This Row],[Order Date]],FIND("/",SalesData[[#This Row],[Order Date]])+1)-FIND("/",SalesData[[#This Row],[Order Date]])-1)))) -> 42365
A40: 39 | B40: CA-2015-117415 | C40: 12/27/2015 | D40: 12/31/2015 | E40: Standard Class | F40: SN-20710 | G40: Steve Nguyen | H40: Home Office | I40: United States | J40: Houston | K40: Texas | L40: 77041 | M40: Central | N40: FUR-BO-10002545 | O40: Furniture | P40: Bookcases | Q40: Atlantic Metals Mobile 3-Shelf Bookcases, Custom Colors | R40: 532.3992 | S40: 3 | T40: 0.32 | U40: -46.9764 | V40: =IF(ISNUMBER(SalesData[[#This Row],[Order Date]]),DATE(YEAR(SalesData[[#This Row],[Order Date]]),DAY(SalesData[[#This Row],[Order Date]]),MONTH(SalesData[[#This Row],[Order Date]])),DATE(VALUE(RIGHT(SalesData[[#This Row],[Order Date]],4)),VALUE(LEFT(SalesData[[#This Row],[Order Date]],FIND("/",SalesData[[#This Row],[Order Date]])-1)),VALUE(MID(SalesData[[#This Row],[Order Date]],FIND("/",SalesData[[#This Row],[Order Date]])+1,FIND("/",SalesData[[#This Row],[Order Date]],FIND("/",SalesData[[#This Row],[Order Date]])+1)-FIND("/",SalesData[[#This Row],[Order Date]])-1)))) -> 42365
A41: 40 | B41: CA-2015-117415 | C41: 12/27/2015 | D41: 12/31/2015 | E41: Standard Class | F41: SN-20710 | G41: Steve Nguyen | H41: Home Office | I41: United States | J41: Houston | K41: Texas | L41: 77041 | M41: Central | N41: FUR-CH-10004218 | O41: Furniture | P41: Chairs | Q41: Global Fabric Manager's Chair, Dark Gray | R41: 212.058 | S41: 3 | T41: 0.3 | U41: -15.147 | V41: =IF(ISNUMBER(SalesData[[#This Row],[Order Date]]),DATE(YEAR(SalesData[[#This Row],[Order Date]]),DAY(SalesData[[#This Row],[Order Date]]),MONTH(SalesData[[#This Row],[Order Date]])),DATE(VALUE(RIGHT(SalesData[[#This Row],[Order Date]],4)),VALUE(LEFT(SalesData[[#This Row],[Order Date]],FIND("/",SalesData[[#This Row],[Order Date]])-1)),VALUE(MID(SalesData[[#This Row],[Order Date]],FIND("/",SalesData[[#This Row],[Order Date]])+1,FIND("/",SalesData[[#This Row],[Order Date]],FIND("/",SalesData[[#This Row],[Order Date]])+1)-FIND("/",SalesData[[#This Row],[Order Date]])-1)))) -> 42365
A42: 41 | B42: CA-2015-117415 | C42: 12/27/2015 | D42: 12/31/2015 | E42: Standard Class | F42: SN-20710 | G42: Steve Nguyen | H42: Home Office | I42: United States | J42: Houston | K42: Texas | L42: 77041 | M42: Central | N42: TEC-PH-10000486 | O42: Technology | P42: Phones | Q42: Plantronics HL10 Handset Lifter | R42: 371.168 | S42: 4 | T42: 0.2 | U42: 41.7564 | V42: =IF(ISNUMBER(SalesData[[#This Row],[Order Date]]),DATE(YEAR(SalesData[[#This Row],[Order Date]]),DAY(SalesData[[#This Row],[Order Date]]),MONTH(SalesData[[#This Row],[Order Date]])),DATE(VALUE(RIGHT(SalesData[[#This Row],[Order Date]],4)),VALUE(LEFT(SalesData[[#This Row],[Order Date]],FIND("/",SalesData[[#This Row],[Order Date]])-1)),VALUE(MID(SalesData[[#This Row],[Order Date]],FIND("/",SalesData[[#This Row],[Order Date]])+1,FIND("/",SalesData[[#This Row],[Order Date]],FIND("/",SalesData[[#This Row],[Order Date]])+1)-FIND("/",SalesData[[#This Row],[Order Date]])-1)))) -> 42365
A43: 42 | B43: CA-2017-120999 | C43: 43017 | D43: 9/15/2017 | E43: Standard Class | F43: LC-16930 | G43: Linda Cazamias | H43: Corporate | I43: United States | J43: Naperville | K43: Illinois | L43: 60540 | M43: Central | N43: TEC-PH-10004093 | O43: Technology | P43: Phones | Q43: Panasonic Kx-TS550 | R43: 147.168 | S43: 4 | T43: 0.2 | U43: 16.5564 | V43: =IF(ISNUMBER(SalesData[[#This Row],[Order Date]]),DATE(YEAR(SalesData[[#This Row],[Order Date]]),DAY(SalesData[[#This Row],[Order Date]]),MONTH(SalesData[[#This Row],[Order Date]])),DATE(VALUE(RIGHT(SalesData[[#This Row],[Order Date]],4)),VALUE(LEFT(SalesData[[#This Row],[Order Date]],FIND("/",SalesData[[#This Row],[Order Date]])-1)),VALUE(MID(SalesData[[#This Row],[Order Date]],FIND("/",SalesData[[#This Row],[Order Date]])+1,FIND("/",SalesData[[#This Row],[Order Date]],FIND("/",SalesData[[#This Row],[Order Date]])+1)-FIND("/",SalesData[[#This Row],[Order Date]])-1)))) -> 42988
A44: 43 | B44: CA-2016-101343 | C44: 7/17/2016 | D44: 7/22/2016 | E44: Standard Class | F44: RA-19885 | G44: Ruben Ausman | H44: Corporate | I44: United States | J44: Los Angeles | K44: California | L44: 90049 | M44: West | N44: OFF-ST-10003479 | O44: Office Supplies | P44: Storage | Q44: Eldon Base for stackable storage shelf, platinum | R44: 77.88 | S44: 2 | T44: 0 | U44: 3.894 | V44: =IF(ISNUMBER(SalesData[[#This Row],[Order Date]]),DATE(YEAR(SalesData[[#This Row],[Order Date]]),DAY(SalesData[[#This Row],[Order Date]]),MONTH(SalesData[[#This Row],[Order Date]])),DATE(VALUE(RIGHT(SalesData[[#This Row],[Order Date]],4)),VALUE(LEFT(SalesData[[#This Row],[Order Date]],FIND("/",SalesData[[#This Row],[Order Date]])-1)),VALUE(MID(SalesData[[#This Row],[Order Date]],FIND("/",SalesData[[#This Row],[Order Date]])+1,FIND("/",SalesData[[#This Row],[Order Date]],FIND("/",SalesData[[#This Row],[Order Date]])+1)-FIND("/",SalesData[[#This Row],[Order Date]])-1)))) -> 42568
A45: 44 | B45: CA-2017-139619 | C45: 9/19/2017 | D45: 9/23/2017 | E45: Standard Class | F45: ES-14080 | G45: Erin Smith | H45: Corporate | I45: United States | J45: Melbourne | K45: Florida | L45: 32935 | M45: South | N45: OFF-ST-10003282 | O45: Office Supplies | P45: Storage | Q45: Advantus 10-Drawer Portable Organizer, Chrome Metal Frame, Smoke Drawers | R45: 95.616 | S45: 2 | T45: 0.2 | U45: 9.5616 | V45: =IF(ISNUMBER(SalesData[[#This Row],[Order Date]]),DATE(YEAR(SalesData[[#This Row],[Order Date]]),DAY(SalesData[[#This Row],[Order Date]]),MONTH(SalesData[[#This Row],[Order Date]])),DATE(VALUE(RIGHT(SalesData[[#This Row],[Order Date]],4)),VALUE(LEFT(SalesData[[#This Row],[Order Date]],FIND("/",SalesData[[#This Row],[Order Date]])-1)),VALUE(MID(SalesData[[#This Row],[Order Date]],FIND("/",SalesData[[#This Row],[Order Date]])+1,FIND("/",SalesData[[#This Row],[Order Date]],FIND("/",SalesData[[#This Row],[Order Date]])+1)-FIND("/",SalesData[[#This Row],[Order Date]])-1)))) -> 42997
A46: 45 | B46: CA-2016-118255 | C46: 42677 | D46: 3/13/2016 | E46: First Class | F46: ON-18715 | G46: Odella Nelson | H46: Corporate | I46: United States | J46: Eagan | K46: Minnesota | L46: 55122 | M46: Central | N46: TEC-AC-10000171 | O46: Technology | P46: Accessories | Q46: Verbatim 25 GB 6x Blu-ray Single Layer Recordable Disc, 25/Pack | R46: 45.98 | S46: 2 | T46: 0 | U46: 19.7714 | V46: =IF(ISNUMBER(SalesData[[#This Row],[Order Date]]),DATE(YEAR(SalesData[[#This Row],[Order Date]]),DAY(SalesData[[#This Row],[Order Date]]),MONTH(SalesData[[#This Row],[Order Date]])),DATE(VALUE(RIGHT(SalesData[[#This Row],[Order Date]],4)),VALUE(LEFT(SalesData[[#This Row],[Order Date]],FIND("/",SalesData[[#This Row],[Order Date]])-1)),VALUE(MID(SalesData[[#This Row],[Order Date]],FIND("/",SalesData[[#This Row],[Order Date]])+1,FIND("/",SalesData[[#This Row],[Order Date]],FIND("/",SalesData[[#This Row],[Order Date]])+1)-FIND("/",SalesData[[#This Row],[Order Date]])-1)))) -> 42440
A47: 46 | B47: CA-2016-118255 | C47: 42677 | D47: 3/13/2016 | E47: First Class | F47: ON-18715 | G47: Odella Nelson | H47: Corporate | I47: United States | J47: Eagan | K47: Minnesota | L47: 55122 | M47: Central | N47: OFF-BI-10003291 | O47: Office Supplies | P47: Binders | Q47: Wilson Jones Leather-Like Binders with DublLock Round Rings | R47: 17.46 | S47: 2 | T47: 0 | U47: 8.2062 | V47: =IF(ISNUMBER(SalesData[[#This Row],[Order Date]]),DATE(YEAR(SalesData[[#This Row],[Order Date]]),DAY(SalesData[[#This Row],[Order Date]]),MONTH(SalesData[[#This Row],[Order Date]])),DATE(VALUE(RIGHT(SalesData[[#This Row],[Order Date]],4)),VALUE(LEFT(SalesData[[#This Row],[Order Date]],FIND("/",SalesData[[#This Row],[Order Date]])-1)),VALUE(MID(SalesData[[#This Row],[Order Date]],FIND("/",SalesData[[#This Row],[Order Date]])+1,FIND("/",SalesData[[#This Row],[Order Date]],FIND("/",SalesData[[#This Row],[Order Date]])+1)-FIND("/",SalesData[[#This Row],[Order Date]])-1)))) -> 42440
A48: 47 | B48: CA-2014-146703 | C48: 10/20/2014 | D48: 10/25/2014 | E48: Second Class | F48: PO-18865 | G48: Patrick O'Donnell | H48: Consumer | I48: United States | J48: Westland | K48: Michigan | L48: 48185 | M48: Central | N48: OFF-ST-10001713 | O48: Office Supplies | P48: Storage | Q48: Gould Plastics 9-Pocket Panel Bin, 18-3/8w x 5-1/4d x 20-1/2h, Black | R48: 211.96 | S48: 4 | T48: 0 | U48: 8.4784 | V48: =IF(ISNUMBER(SalesData[[#This Row],[Order Date]]),DATE(YEAR(SalesData[[#This Row],[Order Date]]),DAY(SalesData[[#This Row],[Order Date]]),MONTH(SalesData[[#This Row],[Order Date]])),DATE(VALUE(RIGHT(SalesData[[#This Row],[Order Date]],4)),VALUE(LEFT(SalesData[[#This Row],[Order Date]],FIND("/",SalesData[[#This Row],[Order Date]])-1)),VALUE(MID(SalesData[[#This Row],[Order Date]],FIND("/",SalesData[[#This Row],[Order Date]])+1,FIND("/",SalesData[[#This Row],[Order Date]],FIND("/",SalesData[[#This Row],[Order Date]])+1)-FIND("/",SalesData[[#This Row],[Order Date]])-1)))) -> 41932
A49: 48 | B49: CA-2016-169194 | C49: 6/20/2016 | D49: 6/25/2016 | E49: Standard Class | F49: LH-16900 | G49: Lena Hernandez | H49: Consumer | I49: United States | J49: Dover | K49: Delaware | L49: 19901 | M49: East | N49: TEC-AC-10002167 | O49: Technology | P49: Accessories | Q49: Imation 8gb Micro Traveldrive Usb 2.0 Flash Drive | R49: 45 | S49: 3 | T49: 0 | U49: 4.95 | V49: =IF(ISNUMBER(SalesData[[#This Row],[Order Date]]),DATE(YEAR(SalesData[[#This Row],[Order Date]]),DAY(SalesData[[#This Row],[Order Date]]),MONTH(SalesData[[#This Row],[Order Date]])),DATE(VALUE(RIGHT(SalesData[[#This Row],[Order Date]],4)),VALUE(LEFT(SalesData[[#This Row],[Order Date]],FIND("/",SalesData[[#This Row],[Order Date]])-1)),VALUE(MID(SalesData[[#This Row],[Order Date]],FIND("/",SalesData[[#This Row],[Order Date]])+1,FIND("/",SalesData[[#This Row],[Order Date]],FIND("/",SalesData[[#This Row],[Order Date]])+1)-FIND("/",SalesData[[#This Row],[Order Date]])-1)))) -> 42541
A50: 49 | B50: CA-2016-169194 | C50: 6/20/2016 | D50: 6/25/2016 | E50: Standard Class | F50: LH-16900 | G50: Lena Hernandez | H50: Consumer | I50: United States | J50: Dover | K50: Delaware | L50: 19901 | M50: East | N50: TEC-PH-10003988 | O50: Technology | P50: Phones | Q50: LF Elite 3D Dazzle Designer Hard Case Cover, Lf Stylus Pen and Wiper For Apple Iphone 5c Mini Lite | R50: 21.8 | S50: 2 | T50: 0 | U50: 6.104 | V50: =IF(ISNUMBER(SalesData[[#This Row],[Order Date]]),DATE(YEAR(SalesData[[#This Row],[Order Date]]),DAY(SalesData[[#This Row],[Order Date]]),MONTH(SalesData[[#This Row],[Order Date]])),DATE(VALUE(RIGHT(SalesData[[#This Row],[Order Date]],4)),VALUE(LEFT(SalesData[[#This Row],[Order Date]],FIND("/",SalesData[[#This Row],[Order Date]])-1)),VALUE(MID(SalesData[[#This Row],[Order Date]],FIND("/",SalesData[[#This Row],[Order Date]])+1,FIND("/",SalesData[[#This Row],[Order Date]],FIND("/",SalesData[[#This Row],[Order Date]])+1)-FIND("/",SalesData[[#This Row],[Order Date]])-1)))) -> 42541
A51: 50 | B51: CA-2015-115742 | C51: 4/18/2015 | D51: 4/22/2015 | E51: Standard Class | F51: DP-13000 | G51: Darren Powers | H51: Consumer | I51: United States | J51: New Albany | K51: Indiana | L51: 47150 | M51: Central | N51: OFF-BI-10004410 | O51: Office Supplies | P51: Binders | Q51: C-Line Peel & Stick Add-On Filing Pockets, 8-3/4 x 5-1/8, 10/Pack | R51: 38.22 | S51: 6 | T51: 0 | U51: 17.9634 | V51: =IF(ISNUMBER(SalesData[[#This Row],[Order Date]]),DATE(YEAR(SalesData[[#This Row],[Order Date]]),DAY(SalesData[[#This Row],[Order Date]]),MONTH(SalesData[[#This Row],[Order Date]])),DATE(VALUE(RIGHT(SalesData[[#This Row],[Order Date]],4)),VALUE(LEFT(SalesData[[#This Row],[Order Date]],FIND("/",SalesData[[#This Row],[Order Date]])-1)),VALUE(MID(SalesData[[#This Row],[Order Date]],FIND("/",SalesData[[#This Row],[Order Date]])+1,FIND("/",SalesData[[#This Row],[Order Date]],FIND("/",SalesData[[#This Row],[Order Date]])+1)-FIND("/",SalesData[[#This Row],[Order Date]])-1)))) -> 42112
A52: 51 | B52: CA-2015-115742 | C52: 4/18/2015 | D52: 4/22/2015 | E52: Standard Class | F52: DP-13000 | G52: Darren Powers | H52: Consumer | I52: United States | J52: New Albany | K52: Indiana | L52: 47150 | M52: Central | N52: OFF-LA-10002762 | O52: Office Supplies | P52: Labels | Q52: Avery 485 | R52: 75.18 | S52: 6 | T52: 0 | U52: 35.3346 | V52: =IF(ISNUMBER(SalesData[[#This Row],[Order Date]]),DATE(YEAR(SalesData[[#This Row],[Order Date]]),DAY(SalesData[[#This Row],[Order Date]]),MONTH(SalesData[[#This Row],[Order Date]])),DATE(VALUE(RIGHT(SalesData[[#This Row],[Order Date]],4)),VALUE(LEFT(SalesData[[#This Row],[Order Date]],FIND("/",SalesData[[#This Row],[Order Date]])-1)),VALUE(MID(SalesData[[#This Row],[Order Date]],FIND("/",SalesData[[#This Row],[Order Date]])+1,FIND("/",SalesData[[#This Row],[Order Date]],FIND("/",SalesData[[#This Row],[Order Date]])+1)-FIND("/",SalesData[[#This Row],[Order Date]])-1)))) -> 42112
A53: 52 | B53: CA-2015-115742 | C53: 4/18/2015 | D53: 4/22/2015 | E53: Standard Class | F53: DP-13000 | G53: Darren Powers | H53: Consumer | I53: United States | J53: New Albany | K53: Indiana | L53: 47150 | M53: Central | N53: FUR-FU-10001706 | O53: Furniture | P53: Furnishings | Q53: Longer-Life Soft White Bulbs | R53: 6.16 | S53: 2 | T53: 0 | U53: 2.9568 | V53: =IF(ISNUMBER(SalesData[[#This Row],[Order Date]]),DATE(YEAR(SalesData[[#This Row],[Order Date]]),DAY(SalesData[[#This Row],[Order Date]]),MONTH(SalesData[[#This Row],[Order Date]])),DATE(VALUE(RIGHT(SalesData[[#This Row],[Order Date]],4)),VALUE(LEFT(SalesData[[#This Row],[Order Date]],FIND("/",SalesData[[#This Row],[Order Date]])-1)),VALUE(MID(SalesData[[#This Row],[Order Date]],FIND("/",SalesData[[#This Row],[Order Date]])+1,FIND("/",SalesData[[#This Row],[Order Date]],FIND("/",SalesData[[#This Row],[Order Date]])+1)-FIND("/",SalesData[[#This Row],[Order Date]])-1)))) -> 42112
A54: 53 | B54: CA-2015-115742 | C54: 4/18/2015 | D54: 4/22/2015 | E54: Standard Class | F54: DP-13000 | G54: Darren Powers | H54: Consumer | I54: United States | J54: New Albany | K54: Indiana | L54: 47150 | M54: Central | N54: FUR-CH-10003061 | O54: Furniture | P54: Chairs | Q54: Global Leather Task Chair, Black | R54: 89.99 | S54: 1 | T54: 0 | U54: 17.0981 | V54: =IF(ISNUMBER(SalesData[[#This Row],[Order Date]]),DATE(YEAR(SalesData[[#This Row],[Order Date]]),DAY(SalesData[[#This Row],[Order Date]]),MONTH(SalesData[[#This Row],[Order Date]])),DATE(VALUE(RIGHT(SalesData[[#This Row],[Order Date]],4)),VALUE(LEFT(SalesData[[#This Row],[Order Date]],FIND("/",SalesData[[#This Row],[Order Date]])-1)),VALUE(MID(SalesData[[#This Row],[Order Date]],FIND("/",SalesData[[#This Row],[Order Date]])+1,FIND("/",SalesData[[#This Row],[Order Date]],FIND("/",SalesData[[#This Row],[Order Date]])+1)-FIND("/",SalesData[[#This Row],[Order Date]])-1)))) -> 42112
A55: 54 | B55: CA-2016-105816 | C55: 42686 | D55: 12/17/2016 | E55: Standard Class | F55: JM-15265 | G55: Janet Molinari | H55: Corporate | I55: United States | J55: New York City | K55: New York | L55: 10024 | M55: East | N55: OFF-FA-10000304 | O55: Office Supplies | P55: Fasteners | Q55: Advantus Push Pins | R55: 15.26 | S55: 7 | T55: 0 | U55: 6.2566 | V55: =IF(ISNUMBER(SalesData[[#This Row],[Order Date]]),DATE(YEAR(SalesData[[#This Row],[Order Date]]),DAY(SalesData[[#This Row],[Order Date]]),MONTH(SalesData[[#This Row],[Order Date]])),DATE(VALUE(RIGHT(SalesData[[#This Row],[Order Date]],4)),VALUE(LEFT(SalesData[[#This Row],[Order Date]],FIND("/",SalesData[[#This Row],[Order Date]])-1)),VALUE(MID(SalesData[[#This Row],[Order Date]],FIND("/",SalesData[[#This Row],[Order Date]])+1,FIND("/",SalesData[[#This Row],[Order Date]],FIND("/",SalesData[[#This Row],[Order Date]])+1)-FIND("/",SalesData[[#This Row],[Order Date]])-1)))) -> 42715
A56: 55 | B56: CA-2016-105816 | C56: 42686 | D56: 12/17/2016 | E56: Standard Class | F56: JM-15265 | G56: Janet Molinari | H56: Corporate | I56: United States | J56: New York City | K56: New York | L56: 10024 | M56: East | N56: TEC-PH-10002447 | O56: Technology | P56: Phones | Q56: AT&T CL83451 4-Handset Telephone | R56: 1029.95 | S56: 5 | T56: 0 | U56: 298.6855 | V56: =IF(ISNUMBER(SalesData[[#This Row],[Order Date]]),DATE(YEAR(SalesData[[#This Row],[Order Date]]),DAY(SalesData[[#This Row],[Order Date]]),MONTH(SalesData[[#This Row],[Order Date]])),DATE(VALUE(RIGHT(SalesData[[#This Row],[Order Date]],4)),VALUE(LEFT(SalesData[[#This Row],[Order Date]],FIND("/",SalesData[[#This Row],[Order Date]])-1)),VALUE(MID(SalesData[[#This Row],[Order Date]],FIND("/",SalesData[[#This Row],[Order Date]])+1,FIND("/",SalesData[[#This Row],[Order Date]],FIND("/",SalesData[[#This Row],[Order Date]])+1)-FIND("/",SalesData[[#This Row],[Order Date]])-1)))) -> 42715
A57: 56 | B57: CA-2016-111682 | C57: 6/17/2016 | D57: 6/18/2016 | E57: First Class | F57: TB-21055 | G57: Ted Butterfield | H57: Consumer | I57: United States | J57: Troy | K57: New York | L57: 12180 | M57: East | N57: OFF-ST-10000604 | O57: Office Supplies | P57: Storage | Q57: Home/Office Personal File Carts | R57: 208.56 | S57: 6 | T57: 0 | U57: 52.14 | V57: =IF(ISNUMBER(SalesData[[#This Row],[Order Date]]),DATE(YEAR(SalesData[[#This Row],[Order Date]]),DAY(SalesData[[#This Row],[Order Date]]),MONTH(SalesData[[#This Row],[Order Date]])),DATE(VALUE(RIGHT(SalesData[[#This Row],[Order Date]],4)),VALUE(LEFT(SalesData[[#This Row],[Order Date]],FIND("/",SalesData[[#This Row],[Order Date]])-1)),VALUE(MID(SalesData[[#This Row],[Order Date]],FIND("/",SalesData[[#This Row],[Order Date]])+1,FIND("/",SalesData[[#This Row],[Order Date]],FIND("/",SalesData[[#This Row],[Order Date]])+1)-FIND("/",SalesData[[#This Row],[Order Date]])-1)))) -> 42538
A58: 57 | B58: CA-2016-111682 | C58: 6/17/2016 | D58: 6/18/2016 | E58: First Class | F58: TB-21055 | G58: Ted Butterfield | H58: Consumer | I58: United States | J58: Troy | K58: New York | L58: 12180 | M58: East | N58: OFF-PA-10001569 | O58: Office Supplies | P58: Paper | Q58: Xerox 232 | R58: 32.4 | S58: 5 | T58: 0 | U58: 15.552 | V58: =IF(ISNUMBER(SalesData[[#This Row],[Order Date]]),DATE(YEAR(SalesData[[#This Row],[Order Date]]),DAY(SalesData[[#This Row],[Order Date]]),MONTH(SalesData[[#This Row],[Order Date]])),DATE(VALUE(RIGHT(SalesData[[#This Row],[Order Date]],4)),VALUE(LEFT(SalesData[[#This Row],[Order Date]],FIND("/",SalesData[[#This Row],[Order Date]])-1)),VALUE(MID(SalesData[[#This Row],[Order Date]],FIND("/",SalesData[[#This Row],[Order Date]])+1,FIND("/",SalesData[[#This Row],[Order Date]],FIND("/",SalesData[[#This Row],[Order Date]])+1)-FIND("/",SalesData[[#This Row],[Order Date]])-1)))) -> 42538
A59: 58 | B59: CA-2016-111682 | C59: 6/17/2016 | D59: 6/18/2016 | E59: First Class | F59: TB-21055 | G59: Ted Butterfield | H59: Consumer | I59: United States | J59: Troy | K59: New York | L59: 12180 | M59: East | N59: FUR-CH-10003968 | O59: Furniture | P59: Chairs | Q59: Novimex Turbo Task Chair | R59: 319.41 | S59: 5 | T59: 0.1 | U59: 7.098 | V59: =IF(ISNUMBER(SalesData[[#This Row],[Order Date]]),DATE(YEAR(SalesData[[#This Row],[Order Date]]),DAY(SalesData[[#This Row],[Order Date]]),MONTH(SalesData[[#This Row],[Order Date]])),DATE(VALUE(RIGHT(SalesData[[#This Row],[Order Date]],4)),VALUE(LEFT(SalesData[[#This Row],[Order Date]],FIND("/",SalesData[[#This Row],[Order Date]])-1)),VALUE(MID(SalesData[[#This Row],[Order Date]],FIND("/",SalesData[[#This Row],[Order Date]])+1,FIND("/",SalesData[[#This Row],[Order Date]],FIND("/",SalesData[[#This Row],[Order Date]])+1)-FIND("/",SalesData[[#This Row],[Order Date]])-1)))) -> 42538
A60: 59 | B60: CA-2016-111682 | C60: 6/17/2016 | D60: 6/18/2016 | E60: First Class | F60: TB-21055 | G60: Ted Butterfield | H60: Consumer | I60: United States | J60: Troy | K60: New York | L60: 12180 | M60: East | N60: OFF-PA-10000587 | O60: Office Supplies | P60: Paper | Q60: Array Parchment Paper, Assorted Colors | R60: 14.56 | S60: 2 | T60: 0 | U60: 6.9888 | V60: =IF(ISNUMBER(SalesData[[#This Row],[Order Date]]),DATE(YEAR(SalesData[[#This Row],[Order Date]]),DAY(SalesData[[#This Row],[Order Date]]),MONTH(SalesData[[#This Row],[Order Date]])),DATE(VALUE(RIGHT(SalesData[[#This Row],[Order Date]],4)),VALUE(LEFT(SalesData[[#This Row],[Order Date]],FIND("/",SalesData[[#This Row],[Order Date]])-1)),VALUE(MID(SalesData[[#This Row],[Order Date]],FIND("/",SalesData[[#This Row],[Order Date]])+1,FIND("/",SalesData[[#This Row],[Order Date]],FIND("/",SalesData[[#This Row],[Order Date]])+1)-FIND("/",SalesData[[#This Row],[Order Date]])-1)))) -> 42538
A61: 60 | B61: CA-2016-111682 | C61: 6/17/2016 | D61: 6/18/2016 | E61: First Class | F61: TB-21055 | G61: Ted Butterfield | H61: Consumer | I61: United States | J61: Troy | K61: New York | L61: 12180 | M61: East | N61: TEC-AC-10002167 | O61: Technology | P61: Accessories | Q61: Imation 8gb Micro Traveldrive Usb 2.0 Flash Drive | R61: 30 | S61: 2 | T61: 0 | U61: 3.3 | V61: =IF(ISNUMBER(SalesData[[#This Row],[Order Date]]),DATE(YEAR(SalesData[[#This Row],[Order Date]]),DAY(SalesData[[#This Row],[Order Date]]),MONTH(SalesData[[#This Row],[Order Date]])),DATE(VALUE(RIGHT(SalesData[[#This Row],[Order Date]],4)),VALUE(LEFT(SalesData[[#This Row],[Order Date]],FIND("/",SalesData[[#This Row],[Order Date]])-1)),VALUE(MID(SalesData[[#This Row],[Order Date]],FIND("/",SalesData[[#This Row],[Order Date]])+1,FIND("/",SalesData[[#This Row],[Order Date]],FIND("/",SalesData[[#This Row],[Order Date]])+1)-FIND("/",SalesData[[#This Row],[Order Date]])-1)))) -> 42538
A62: 61 | B62: CA-2016-111682 | C62: 6/17/2016 | D62: 6/18/2016 | E62: First Class | F62: TB-21055 | G62: Ted Butterfield | H62: Consumer | I62: United States | J62: Troy | K62: New York | L62: 12180 | M62: East | N62: OFF-BI-10001460 | O62: Office Supplies | P62: Binders | Q62: Plastic Binding Combs | R62: 48.48 | S62: 4 | T62: 0.2 | U62: 16.362 | V62: =IF(ISNUMBER(SalesData[[#This Row],[Order Date]]),DATE(YEAR(SalesData[[#This Row],[Order Date]]),DAY(SalesData[[#This Row],[Order Date]]),MONTH(SalesData[[#This Row],[Order Date]])),DATE(VALUE(RIGHT(SalesData[[#This Row],[Order Date]],4)),VALUE(LEFT(SalesData[[#This Row],[Order Date]],FIND("/",SalesData[[#This Row],[Order Date]])-1)),VALUE(MID(SalesData[[#This Row],[Order Date]],FIND("/",SalesData[[#This Row],[Order Date]])+1,FIND("/",SalesData[[#This Row],[Order Date]],FIND("/",SalesData[[#This Row],[Order Date]])+1)-FIND("/",SalesData[[#This Row],[Order Date]])-1)))) -> 42538
A63: 62 | B63: CA-2016-111682 | C63: 6/17/2016 | D63: 6/18/2016 | E63: First Class | F63: TB-21055 | G63: Ted Butterfield | H63: Consumer | I63: United States | J63: Troy | K63: New York | L63: 12180 | M63: East | N63: OFF-AR-10001868 | O63: Office Supplies | P63: Art | Q63: Prang Dustless Chalk Sticks | R63: 1.68 | S63: 1 | T63: 0 | U63: 0.84 | V63: =IF(ISNUMBER(SalesData[[#This Row],[Order Date]]),DATE(YEAR(SalesData[[#This Row],[Order Date]]),DAY(SalesData[[#This Row],[Order Date]]),MONTH(SalesData[[#This Row],[Order Date]])),DATE(VALUE(RIGHT(SalesData[[#This Row],[Order Date]],4)),VALUE(LEFT(SalesData[[#This Row],[Order Date]],FIND("/",SalesData[[#This Row],[Order Date]])-1)),VALUE(MID(SalesData[[#This Row],[Order Date]],FIND("/",SalesData[[#This Row],[Order Date]])+1,FIND("/",SalesData[[#This Row],[Order Date]],FIND("/",SalesData[[#This Row],[Order Date]])+1)-FIND("/",SalesData[[#This Row],[Order Date]])-1)))) -> 42538
A64: 63 | B64: CA-2015-135545 | C64: 11/24/2015 | D64: 11/30/2015 | E64: Standard Class | F64: KM-16720 | G64: Kunst Miller | H64: Consumer | I64: United States | J64: Los Angeles | K64: California | L64: 90004 | M64: West | N64: TEC-AC-10004633 | O64: Technology | P64: Accessories | Q64: Verbatim 25 GB 6x Blu-ray Single Layer Recordable Disc, 3/Pack | R64: 13.98 | S64: 2 | T64: 0 | U64: 6.1512 | V64: =IF(ISNUMBER(SalesData[[#This Row],[Order Date]]),DATE(YEAR(SalesData[[#This Row],[Order Date]]),DAY(SalesData[[#This Row],[Order Date]]),MONTH(SalesData[[#This Row],[Order Date]])),DATE(VALUE(RIGHT(SalesData[[#This Row],[Order Date]],4)),VALUE(LEFT(SalesData[[#This Row],[Order Date]],FIND("/",SalesData[[#This Row],[Order Date]])-1)),VALUE(MID(SalesData[[#This Row],[Order Date]],FIND("/",SalesData[[#This Row],[Order Date]])+1,FIND("/",SalesData[[#This Row],[Order Date]],FIND("/",SalesData[[#This Row],[Order Date]])+1)-FIND("/",SalesData[[#This Row],[Order Date]])-1)))) -> 42332
A65: 64 | B65: CA-2015-135545 | C65: 11/24/2015 | D65: 11/30/2015 | E65: Standard Class | F65: KM-16720 | G65: Kunst Miller | H65: Consumer | I65: United States | J65: Los Angeles | K65: California | L65: 90004 | M65: West | N65: OFF-BI-10001078 | O65: Office Supplies | P65: Binders | Q65: Acco PRESSTEX Data Binder with Storage Hooks, Dark Blue, 14 7/8" X 11" | R65: 25.824 | S65: 6 | T65: 0.2 | U65: 9.3612 | V65: =IF(ISNUMBER(SalesData[[#This Row],[Order Date]]),DATE(YEAR(SalesData[[#This Row],[Order Date]]),DAY(SalesData[[#This Row],[Order Date]]),MONTH(SalesData[[#This Row],[Order Date]])),DATE(VALUE(RIGHT(SalesData[[#This Row],[Order Date]],4)),VALUE(LEFT(SalesData[[#This Row],[Order Date]],FIND("/",SalesData[[#This Row],[Order Date]])-1)),VALUE(MID(SalesData[[#This Row],[Order Date]],FIND("/",SalesData[[#This Row],[Order Date]])+1,FIND("/",SalesData[[#This Row],[Order Date]],FIND("/",SalesData[[#This Row],[Order Date]])+1)-FIND("/",SalesData[[#This Row],[Order Date]])-1)))) -> 42332
A66: 65 | B66: CA-2015-135545 | C66: 11/24/2015 | D66: 11/30/2015 | E66: Standard Class | F66: KM-16720 | G66: Kunst Miller | H66: Consumer | I66: United States | J66: Los Angeles | K66: California | L66: 90004 | M66: West | N66: OFF-PA-10003892 | O66: Office Supplies | P66: Paper | Q66: Xerox 1943 | R66: 146.73 | S66: 3 | T66: 0 | U66: 68.9631 | V66: =IF(ISNUMBER(SalesData[[#This Row],[Order Date]]),DATE(YEAR(SalesData[[#This Row],[Order Date]]),DAY(SalesData[[#This Row],[Order Date]]),MONTH(SalesData[[#This Row],[Order Date]])),DATE(VALUE(RIGHT(SalesData[[#This Row],[Order Date]],4)),VALUE(LEFT(SalesData[[#This Row],[Order Date]],FIND("/",SalesData[[#This Row],[Order Date]])-1)),VALUE(MID(SalesData[[#This Row],[Order Date]],FIND("/",SalesData[[#This Row],[Order Date]])+1,FIND("/",SalesData[[#This Row],[Order Date]],FIND("/",SalesData[[#This Row],[Order Date]])+1)-FIND("/",SalesData[[#This Row],[Order Date]])-1)))) -> 42332
A67: 66 | B67: CA-2015-135545 | C67: 11/24/2015 | D67: 11/30/2015 | E67: Standard Class | F67: KM-16720 | G67: Kunst Miller | H67: Consumer | I67: United States | J67: Los Angeles | K67: California | L67: 90004 | M67: West | N67: FUR-FU-10000397 | O67: Furniture | P67: Furnishings | Q67: Luxo Economy Swing Arm Lamp | R67: 79.76 | S67: 4 | T67: 0 | U67: 22.3328 | V67: =IF(ISNUMBER(SalesData[[#This Row],[Order Date]]),DATE(YEAR(SalesData[[#This Row],[Order Date]]),DAY(SalesData[[#This Row],[Order Date]]),MONTH(SalesData[[#This Row],[Order Date]])),DATE(VALUE(RIGHT(SalesData[[#This Row],[Order Date]],4)),VALUE(LEFT(SalesData[[#This Row],[Order Date]],FIND("/",SalesData[[#This Row],[Order Date]])-1)),VALUE(MID(SalesData[[#This Row],[Order Date]],FIND("/",SalesData[[#This Row],[Order Date]])+1,FIND("/",SalesData[[#This Row],[Order Date]],FIND("/",SalesData[[#This Row],[Order Date]])+1)-FIND("/",SalesData[[#This Row],[Order Date]])-1)))) -> 42332
A68: 67 | B68: US-2015-164175 | C68: 4/30/2015 | D68: 42129 | E68: Standard Class | F68: PS-18970 | G68: Paul Stevenson | H68: Home Office | I68: United States | J68: Chicago | K68: Illinois | L68: 60610 | M68: Central | N68: FUR-CH-10001146 | O68: Furniture | P68: Chairs | Q68: Global Value Mid-Back Manager's Chair, Gray | R68: 213.115 | S68: 5 | T68: 0.3 | U68: -15.2225 | V68: =IF(ISNUMBER(SalesData[[#This Row],[Order Date]]),DATE(YEAR(SalesData[[#This Row],[Order Date]]),DAY(SalesData[[#This Row],[Order Date]]),MONTH(SalesData[[#This Row],[Order Date]])),DATE(VALUE(RIGHT(SalesData[[#This Row],[Order Date]],4)),VALUE(LEFT(SalesData[[#This Row],[Order Date]],FIND("/",SalesData[[#This Row],[Order Date]])-1)),VALUE(MID(SalesData[[#This Row],[Order Date]],FIND("/",SalesData[[#This Row],[Order Date]])+1,FIND("/",SalesData[[#This Row],[Order Date]],FIND("/",SalesData[[#This Row],[Order Date]])+1)-FIND("/",SalesData[[#This Row],[Order Date]])-1)))) -> 42124
A69: 68 | B69: CA-2014-106376 | C69: 41771 | D69: 41924 | E69: Standard Class | F69: BS-11590 | G69: Brendan Sweed | H69: Corporate | I69: United States | J69: Gilbert | K69: Arizona | L69: 85234 | M69: West | N69: OFF-AR-10002671 | O69: Office Supplies | P69: Art | Q69: Hunt BOSTON Model 1606 High-Volume Electric Pencil Sharpener, Beige | R69: 1113.024 | S69: 8 | T69: 0.2 | U69: 111.3024 | V69: =IF(ISNUMBER(SalesData[[#This Row],[Order Date]]),DATE(YEAR(SalesData[[#This Row],[Order Date]]),DAY(SalesData[[#This Row],[Order Date]]),MONTH(SalesData[[#This Row],[Order Date]])),DATE(VALUE(RIGHT(SalesData[[#This Row],[Order Date]],4)),VALUE(LEFT(SalesData[[#This Row],[Order Date]],FIND("/",SalesData[[#This Row],[Order Date]])-1)),VALUE(MID(SalesData[[#This Row],[Order Date]],FIND("/",SalesData[[#This Row],[Order Date]])+1,FIND("/",SalesData[[#This Row],[Order Date]],FIND("/",SalesData[[#This Row],[Order Date]])+1)-FIND("/",SalesData[[#This Row],[Order Date]])-1)))) -> 41978
A70: 69 | B70: CA-2014-106376 | C70: 41771 | D70: 41924 | E70: Standard Class | F70: BS-11590 | G70: Brendan Sweed | H70: Corporate | I70: United States | J70: Gilbert | K70: Arizona | L70: 85234 | M70: West | N70: TEC-PH-10002726 | O70: Technology | P70: Phones | Q70: netTALK DUO VoIP Telephone Service | R70: 167.968 | S70: 4 | T70: 0.2 | U70: 62.988 | V70: =IF(ISNUMBER(SalesData[[#This Row],[Order Date]]),DATE(YEAR(SalesData[[#This Row],[Order Date]]),DAY(SalesData[[#This Row],[Order Date]]),MONTH(SalesData[[#This Row],[Order Date]])),DATE(VALUE(RIGHT(SalesData[[#This Row],[Order Date]],4)),VALUE(LEFT(SalesData[[#This Row],[Order Date]],FIND("/",SalesData[[#This Row],[Order Date]])-1)),VALUE(MID(SalesData[[#This Row],[Order Date]],FIND("/",SalesData[[#This Row],[Order Date]])+1,FIND("/",SalesData[[#This Row],[Order Date]],FIND("/",SalesData[[#This Row],[Order Date]])+1)-FIND("/",SalesData[[#This Row],[Order Date]])-1)))) -> 41978
A71: 70 | B71: CA-2016-119823 | C71: 42466 | D71: 42527 | E71: First Class | F71: KD-16270 | G71: Karen Daniels | H71: Consumer | I71: United States | J71: Springfield | K71: Virginia | L71: 22153 | M71: South | N71: OFF-PA-10000482 | O71: Office Supplies | P71: Paper | Q71: Snap-A-Way Black Print Carbonless Ruled Speed Letter, Triplicate | R71: 75.88 | S71: 2 | T71: 0 | U71: 35.6636 | V71: =IF(ISNUMBER(SalesData[[#This Row],[Order Date]]),DATE(YEAR(SalesData[[#This Row],[Order Date]]),DAY(SalesData[[#This Row],[Order Date]]),MONTH(SalesData[[#This Row],[Order Date]])),DATE(VALUE(RIGHT(SalesData[[#This Row],[Order Date]],4)),VALUE(LEFT(SalesData[[#This Row],[Order Date]],FIND("/",SalesData[[#This Row],[Order Date]])-1)),VALUE(MID(SalesData[[#This Row],[Order Date]],FIND("/",SalesData[[#This Row],[Order Date]])+1,FIND("/",SalesData[[#This Row],[Order Date]],FIND("/",SalesData[[#This Row],[Order Date]])+1)-FIND("/",SalesData[[#This Row],[Order Date]])-1)))) -> 42525
A72: 71 | B72: CA-2016-106075 | C72: 9/18/2016 | D72: 9/23/2016 | E72: Standard Class | F72: HM-14980 | G72: Henry MacAllister | H72: Consumer | I72: United States | J72: New York City | K72: New York | L72: 10009 | M72: East | N72: OFF-BI-10004654 | O72: Office Supplies | P72: Binders | Q72: Avery Binding System Hidden Tab Executive Style Index Sets | R72: 4.616 | S72: 1 | T72: 0.2 | U72: 1.731 | V72: =IF(ISNUMBER(SalesData[[#This Row],[Order Date]]),DATE(YEAR(SalesData[[#This Row],[Order Date]]),DAY(SalesData[[#This Row],[Order Date]]),MONTH(SalesData[[#This Row],[Order Date]])),DATE(VALUE(RIGHT(SalesData[[#This Row],[Order Date]],4)),VALUE(LEFT(SalesData[[#This Row],[Order Date]],FIND("/",SalesData[[#This Row],[Order Date]])-1)),VALUE(MID(SalesData[[#This Row],[Order Date]],FIND("/",SalesData[[#This Row],[Order Date]])+1,FIND("/",SalesData[[#This Row],[Order Date]],FIND("/",SalesData[[#This Row],[Order Date]])+1)-FIND("/",SalesData[[#This Row],[Order Date]])-1)))) -> 42631
A73: 72 | B73: CA-2017-114440 | C73: 9/14/2017 | D73: 9/17/2017 | E73: Second Class | F73: TB-21520 | G73: Tracy Blumstein | H73: Consumer | I73: United States | J73: Jackson | K73: Michigan | L73: 49201 | M73: Central | N73: OFF-PA-10004675 | O73: Office Supplies | P73: Paper | Q73: Telephone Message Books with Fax/Mobile Section, 5 1/2" x 3 3/16" | R73: 19.05 | S73: 3 | T73: 0 | U73: 8.763 | V73: =IF(ISNUMBER(SalesData[[#This Row],[Order Date]]),DATE(YEAR(SalesData[[#This Row],[Order Date]]),DAY(SalesData[[#This Row],[Order Date]]),MONTH(SalesData[[#This Row],[Order Date]])),DATE(VALUE(RIGHT(SalesData[[#This Row],[Order Date]],4)),VALUE(LEFT(SalesData[[#This Row],[Order Date]],FIND("/",SalesData[[#This Row],[Order Date]])-1)),VALUE(MID(SalesData[[#This Row],[Order Date]],FIND("/",SalesData[[#This Row],[Order Date]])+1,FIND("/",SalesData[[#This Row],[Order Date]],FIND("/",SalesData[[#This Row],[Order Date]])+1)-FIND("/",SalesData[[#This Row],[Order Date]])-1)))) -> 42992
A74: 73 | B74: US-2015-134026 | C74: 4/26/2015 | D74: 42040 | E74: Standard Class | F74: JE-15745 | G74: Joel Eaton | H74: Consumer | I74: United States | J74: Memphis | K74: Tennessee | L74: 38109 | M74: South | N74: FUR-CH-10000513 | O74: Furniture | P74: Chairs | Q74: High-Back Leather Manager's Chair | R74: 831.936 | S74: 8 | T74: 0.2 | U74: -114.3912 | V74: =IF(ISNUMBER(SalesData[[#This Row],[Order Date]]),DATE(YEAR(SalesData[[#This Row],[Order Date]]),DAY(SalesData[[#This Row],[Order Date]]),MONTH(SalesData[[#This Row],[Order Date]])),DATE(VALUE(RIGHT(SalesData[[#This Row],[Order Date]],4)),VALUE(LEFT(SalesData[[#This Row],[Order Date]],FIND("/",SalesData[[#This Row],[Order Date]])-1)),VALUE(MID(SalesData[[#This Row],[Order Date]],FIND("/",SalesData[[#This Row],[Order Date]])+1,FIND("/",SalesData[[#This Row],[Order Date]],FIND("/",SalesData[[#This Row],[Order Date]])+1)-FIND("/",SalesData[[#This Row],[Order Date]])-1)))) -> 42120
A75: 74 | B75: US-2015-134026 | C75: 4/26/2015 | D75: 42040 | E75: Standard Class | F75: JE-15745 | G75: Joel Eaton | H75: Consumer | I75: United States | J75: Memphis | K75: Tennessee | L75: 38109 | M75: South | N75: FUR-FU-10003708 | O75: Furniture | P75: Furnishings | Q75: Tenex Traditional Chairmats for Medium Pile Carpet, Standard Lip, 36" x 48" | R75: 97.04 | S75: 2 | T75: 0.2 | U75: 1.213 | V75: =IF(ISNUMBER(SalesData[[#This Row],[Order Date]]),DATE(YEAR(SalesData[[#This Row],[Order Date]]),DAY(SalesData[[#This Row],[Order Date]]),MONTH(SalesData[[#This Row],[Order Date]])),DATE(VALUE(RIGHT(SalesData[[#This Row],[Order Date]],4)),VALUE(LEFT(SalesData[[#This Row],[Order Date]],FIND("/",SalesData[[#This Row],[Order Date]])-1)),VALUE(MID(SalesData[[#This Row],[Order Date]],FIND("/",SalesData[[#This Row],[Order Date]])+1,FIND("/",SalesData[[#This Row],[Order Date]],FIND("/",SalesData[[#This Row],[Order Date]])+1)-FIND("/",SalesData[[#This Row],[Order Date]])-1)))) -> 42120
A76: 75 | B76: US-2015-134026 | C76: 4/26/2015 | D76: 42040 | E76: Standard Class | F76: JE-15745 | G76: Joel Eaton | H76: Consumer | I76: United States | J76: Memphis | K76: Tennessee | L76: 38109 | M76: South | N76: OFF-ST-10004123 | O76: Office Supplies | P76: Storage | Q76: Safco Industrial Wire Shelving System | R76: 72.784 | S76: 1 | T76: 0.2 | U76: -18.196 | V76: =IF(ISNUMBER(SalesData[[#This Row],[Order Date]]),DATE(YEAR(SalesData[[#This Row],[Order Date]]),DAY(SalesData[[#This Row],[Order Date]]),MONTH(SalesData[[#This Row],[Order Date]])),DATE(VALUE(RIGHT(SalesData[[#This Row],[Order Date]],4)),VALUE(LEFT(SalesData[[#This Row],[Order Date]],FIND("/",SalesData[[#This Row],[Order Date]])-1)),VALUE(MID(SalesData[[#This Row],[Order Date]],FIND("/",SalesData[[#This Row],[Order Date]])+1,FIND("/",SalesData[[#This Row],[Order Date]],FIND("/",SalesData[[#This Row],[Order Date]])+1)-FIND("/",SalesData[[#This Row],[Order Date]])-1)))) -> 42120
A77: 76 | B77: US-2017-118038 | C77: 42990 | D77: 43051 | E77: First Class | F77: KB-16600 | G77: Ken Brennan | H77: Corporate | I77: United States | J77: Houston | K77: Texas | L77: 77041 | M77: Central | N77: OFF-BI-10004182 | O77: Office Supplies | P77: Binders | Q77: Economy Binders | R77: 1.248 | S77: 3 | T77: 0.8 | U77: -1.9344 | V77: =IF(ISNUMBER(SalesData[[#This Row],[Order Date]]),DATE(YEAR(SalesData[[#This Row],[Order Date]]),DAY(SalesData[[#This Row],[Order Date]]),MONTH(SalesData[[#This Row],[Order Date]])),DATE(VALUE(RIGHT(SalesData[[#This Row],[Order Date]],4)),VALUE(LEFT(SalesData[[#This Row],[Order Date]],FIND("/",SalesData[[#This Row],[Order Date]])-1)),VALUE(MID(SalesData[[#This Row],[Order Date]],FIND("/",SalesData[[#This Row],[Order Date]])+1,FIND("/",SalesData[[#This Row],[Order Date]],FIND("/",SalesData[[#This Row],[Order Date]])+1)-FIND("/",SalesData[[#This Row],[Order Date]])-1)))) -> 43078
A78: 77 | B78: US-2017-118038 | C78: 42990 | D78: 43051 | E78: First Class | F78: KB-16600 | G78: Ken Brennan | H78: Corporate | I78: United States | J78: Houston | K78: Texas | L78: 77041 | M78: Central | N78: FUR-FU-10000260 | O78: Furniture | P78: Furnishings | Q78: 6" Cubicle Wall Clock, Black | R78: 9.708 | S78: 3 | T78: 0.6 | U78: -5.8248 | V78: =IF(ISNUMBER(SalesData[[#This Row],[Order Date]]),DATE(YEAR(SalesData[[#This Row],[Order Date]]),DAY(SalesData[[#This Row],[Order Date]]),MONTH(SalesData[[#This Row],[Order Date]])),DATE(VALUE(RIGHT(SalesData[[#This Row],[Order Date]],4)),VALUE(LEFT(SalesData[[#This Row],[Order Date]],FIND("/",SalesData[[#This Row],[Order Date]])-1)),VALUE(MID(SalesData[[#This Row],[Order Date]],FIND("/",SalesData[[#This Row],[Order Date]])+1,FIND("/",SalesData[[#This Row],[Order Date]],FIND("/",SalesData[[#This Row],[Order Date]])+1)-FIND("/",SalesData[[#This Row],[Order Date]])-1)))) -> 43078
A79: 78 | B79: US-2017-118038 | C79: 42990 | D79: 43051 | E79: First Class | F79: KB-16600 | G79: Ken Brennan | H79: Corporate | I79: United States | J79: Houston | K79: Texas | L79: 77041 | M79: Central | N79: OFF-ST-10000615 | O79: Office Supplies | P79: Storage | Q79: SimpliFile Personal File, Black Granite, 15w x 6-15/16d x 11-1/4h | R79: 27.24 | S79: 3 | T79: 0.2 | U79: 2.724 | V79: =IF(ISNUMBER(SalesData[[#This Row],[Order Date]]),DATE(YEAR(SalesData[[#This Row],[Order Date]]),DAY(SalesData[[#This Row],[Order Date]]),MONTH(SalesData[[#This Row],[Order Date]])),DATE(VALUE(RIGHT(SalesData[[#This Row],[Order Date]],4)),VALUE(LEFT(SalesData[[#This Row],[Order Date]],FIND("/",SalesData[[#This Row],[Order Date]])-1)),VALUE(MID(SalesData[[#This Row],[Order Date]],FIND("/",SalesData[[#This Row],[Order Date]])+1,FIND("/",SalesData[[#This Row],[Order Date]],FIND("/",SalesData[[#This Row],[Order Date]])+1)-FIND("/",SalesData[[#This Row],[Order Date]])-1)))) -> 43078
A80: 79 | B80: US-2014-147606 | C80: 11/26/2014 | D80: 41651 | E80: Second Class | F80: JE-15745 | G80: Joel Eaton | H80: Consumer | I80: United States | J80: Houston | K80: Texas | L80: 77070 | M80: Central | N80: FUR-FU-10003194 | O80: Furniture | P80: Furnishings | Q80: Eldon Expressions Desk Accessory, Wood Pencil Holder, Oak | R80: 19.3 | S80: 5 | T80: 0.6 | U80: -14.475 | V80: =IF(ISNUMBER(SalesData[[#This Row],[Order Date]]),DATE(YEAR(SalesData[[#This Row],[Order Date]]),DAY(SalesData[[#This Row],[Order Date]]),MONTH(SalesData[[#This Row],[Order Date]])),DATE(VALUE(RIGHT(SalesData[[#This Row],[Order Date]],4)),VALUE(LEFT(SalesData[[#This Row],[Order Date]],FIND("/",SalesData[[#This Row],[Order Date]])-1)),VALUE(MID(SalesData[[#This Row],[Order Date]],FIND("/",SalesData[[#This Row],[Order Date]])+1,FIND("/",SalesData[[#This Row],[Order Date]],FIND("/",SalesData[[#This Row],[Order Date]])+1)-FIND("/",SalesData[[#This Row],[Order Date]])-1)))) -> 41969
A81: 80 | B81: CA-2016-127208 | C81: 42710 | D81: 6/15/2016 | E81: First Class | F81: SC-20770 | G81: Stewart Carmichael | H81: Corporate | I81: United States | J81: Decatur | K81: Alabama | L81: 35601 | M81: South | N81: OFF-AP-10002118 | O81: Office Supplies | P81: Appliances | Q81: 1.7 Cubic Foot Compact "Cube" Office Refrigerators | R81: 208.16 | S81: 1 | T81: 0 | U81: 56.2032 | V81: =IF(ISNUMBER(SalesData[[#This Row],[Order Date]]),DATE(YEAR(SalesData[[#This Row],[Order Date]]),DAY(SalesData[[#This Row],[Order Date]]),MONTH(SalesData[[#This Row],[Order Date]])),DATE(VALUE(RIGHT(SalesData[[#This Row],[Order Date]],4)),VALUE(LEFT(SalesData[[#This Row],[Order Date]],FIND("/",SalesData[[#This Row],[Order Date]])-1)),VALUE(MID(SalesData[[#This Row],[Order Date]],FIND("/",SalesData[[#This Row],[Order Date]])+1,FIND("/",SalesData[[#This Row],[Order Date]],FIND("/",SalesData[[#This Row],[Order Date]])+1)-FIND("/",SalesData[[#This Row],[Order Date]])-1)))) -> 42533
A82: 81 | B82: CA-2016-127208 | C82: 42710 | D82: 6/15/2016 | E82: First Class | F82: SC-20770 | G82: Stewart Carmichael | H82: Corporate | I82: United States | J82: Decatur | K82: Alabama | L82: 35601 | M82: South | N82: OFF-BI-10002309 | O82: Office Supplies | P82: Binders | Q82: Avery Heavy-Duty EZD Binder With Locking Rings | R82: 16.74 | S82: 3 | T82: 0 | U82: 8.0352 | V82: =IF(ISNUMBER(SalesData[[#This Row],[Order Date]]),DATE(YEAR(SalesData[[#This Row],[Order Date]]),DAY(SalesData[[#This Row],[Order Date]]),MONTH(SalesData[[#This Row],[Order Date]])),DATE(VALUE(RIGHT(SalesData[[#This Row],[Order Date]],4)),VALUE(LEFT(SalesData[[#This Row],[Order Date]],FIND("/",SalesData[[#This Row],[Order Date]])-1)),VALUE(MID(SalesData[[#This Row],[Order Date]],FIND("/",SalesData[[#This Row],[Order Date]])+1,FIND("/",SalesData[[#This Row],[Order Date]],FIND("/",SalesData[[#This Row],[Order Date]])+1)-FIND("/",SalesData[[#This Row],[Order Date]])-1)))) -> 42533
A83: 82 | B83: CA-2014-139451 | C83: 41983 | D83: 10/16/2014 | E83: Standard Class | F83: DN-13690 | G83: Duane Noonan | H83: Consumer | I83: United States | J83: San Francisco | K83: California | L83: 94122 | M83: West | N83: OFF-AR-10002053 | O83: Office Supplies | P83: Art | Q83: Premium Writing Pencils, Soft, #2 by Central Association for the Blind | R83: 14.9 | S83: 5 | T83: 0 | U83: 4.172 | V83: =IF(ISNUMBER(SalesData[[#This Row],[Order Date]]),DATE(YEAR(SalesData[[#This Row],[Order Date]]),DAY(SalesData[[#This Row],[Order Date]]),MONTH(SalesData[[#This Row],[Order Date]])),DATE(VALUE(RIGHT(SalesData[[#This Row],[Order Date]],4)),VALUE(LEFT(SalesData[[#This Row],[Order Date]],FIND("/",SalesData[[#This Row],[Order Date]])-1)),VALUE(MID(SalesData[[#This Row],[Order Date]],FIND("/",SalesData[[#This Row],[Order Date]])+1,FIND("/",SalesData[[#This Row],[Order Date]],FIND("/",SalesData[[#This Row],[Order Date]])+1)-FIND("/",SalesData[[#This Row],[Order Date]])-1)))) -> 41924
A84: 83 | B84: CA-2014-139451 | C84: 41983 | D84: 10/16/2014 | E84: Standard Class | F84: DN-13690 | G84: Duane Noonan | H84: Consumer | I84: United States | J84: San Francisco | K84: California | L84: 94122 | M84: West | N84: OFF-ST-10002370 | O84: Office Supplies | P84: Storage | Q84: Sortfiler Multipurpose Personal File Organizer, Black | R84: 21.39 | S84: 1 | T84: 0 | U84: 6.2031 | V84: =IF(ISNUMBER(SalesData[[#This Row],[Order Date]]),DATE(YEAR(SalesData[[#This Row],[Order Date]]),DAY(SalesData[[#This Row],[Order Date]]),MONTH(SalesData[[#This Row],[Order Date]])),DATE(VALUE(RIGHT(SalesData[[#This Row],[Order Date]],4)),VALUE(LEFT(SalesData[[#This Row],[Order Date]],FIND("/",SalesData[[#This Row],[Order Date]])-1)),VALUE(MID(SalesData[[#This Row],[Order Date]],FIND("/",SalesData[[#This Row],[Order Date]])+1,FIND("/",SalesData[[#This Row],[Order Date]],FIND("/",SalesData[[#This Row],[Order Date]])+1)-FIND("/",SalesData[[#This Row],[Order Date]])-1)))) -> 41924
A85: 84 | B85: CA-2015-149734 | C85: 42072 | D85: 42225 | E85: Standard Class | F85: JC-16105 | G85: Julie Creighton | H85: Corporate | I85: United States | J85: Durham | K85: North Carolina | L85: 27707 | M85: South | N85: OFF-EN-10000927 | O85: Office Supplies | P85: Envelopes | Q85: Jet-Pak Recycled Peel 'N' Seal Padded Mailers | R85: 200.984 | S85: 7 | T85: 0.2 | U85: 62.8075 | V85: =IF(ISNUMBER(SalesData[[#This Row],[Order Date]]),DATE(YEAR(SalesData[[#This Row],[Order Date]]),DAY(SalesData[[#This Row],[Order Date]]),MONTH(SalesData[[#This Row],[Order Date]])),DATE(VALUE(RIGHT(SalesData[[#This Row],[Order Date]],4)),VALUE(LEFT(SalesData[[#This Row],[Order Date]],FIND("/",SalesData[[#This Row],[Order Date]])-1)),VALUE(MID(SalesData[[#This Row],[Order Date]],FIND("/",SalesData[[#This Row],[Order Date]])+1,FIND("/",SalesData[[#This Row],[Order Date]],FIND("/",SalesData[[#This Row],[Order Date]])+1)-FIND("/",SalesData[[#This Row],[Order Date]])-1)))) -> 42250
A86: 85 | B86: US-2017-119662 | C86: 11/13/2017 | D86: 11/16/2017 | E86: First Class | F86: CS-12400 | G86: Christopher Schild | H86: Home Office | I86: United States | J86: Chicago | K86: Illinois | L86: 60623 | M86: Central | N86: OFF-ST-10003656 | O86: Office Supplies | P86: Storage | Q86: Safco Industrial Wire Shelving | R86: 230.376 | S86: 3 | T86: 0.2 | U86: -48.9549 | V86: =IF(ISNUMBER(SalesData[[#This Row],[Order Date]]),DATE(YEAR(SalesData[[#This Row],[Order Date]]),DAY(SalesData[[#This Row],[Order Date]]),MONTH(SalesData[[#This Row],[Order Date]])),DATE(VALUE(RIGHT(SalesData[[#This Row],[Order Date]],4)),VALUE(LEFT(SalesData[[#This Row],[Order Date]],FIND("/",SalesData[[#This Row],[Order Date]])-1)),VALUE(MID(SalesData[[#This Row],[Order Date]],FIND("/",SalesData[[#This Row],[Order Date]])+1,FIND("/",SalesData[[#This Row],[Order Date]],FIND("/",SalesData[[#This Row],[Order Date]])+1)-FIND("/",SalesData[[#This Row],[Order Date]])-1)))) -> 43052
A87: 86 | B87: CA-2017-140088 | C87: 5/28/2017 | D87: 5/30/2017 | E87: Second Class | F87: PO-18865 | G87: Patrick O'Donnell | H87: Consumer | I87: United States | J87: Columbia | K87: South Carolina | L87: 29203 | M87: South | N87: FUR-CH-10000863 | O87: Furniture | P87: Chairs | Q87: Novimex Swivel Fabric Task Chair | R87: 301.96 | S87: 2 | T87: 0 | U87: 33.2156 | V87: =IF(ISNUMBER(SalesData[[#This Row],[Order Date]]),DATE(YEAR(SalesData[[#This Row],[Order Date]]),DAY(SalesData[[#This Row],[Order Date]]),MONTH(SalesData[[#This Row],[Order Date]])),DATE(VALUE(RIGHT(SalesData[[#This Row],[Order Date]],4)),VALUE(LEFT(SalesData[[#This Row],[Order Date]],FIND("/",SalesData[[#This Row],[Order Date]])-1)),VALUE(MID(SalesData[[#This Row],[Order Date]],FIND("/",SalesData[[#This Row],[Order Date]])+1,FIND("/",SalesData[[#This Row],[Order Date]],FIND("/",SalesData[[#This Row],[Order Date]])+1)-FIND("/",SalesData[[#This Row],[Order Date]])-1)))) -> 42883
A88: 87 | B88: CA-2017-155558 | C88: 10/26/2017 | D88: 42777 | E88: Standard Class | F88: PG-18895 | G88: Paul Gonzalez | H88: Consumer | I88: United States | J88: Rochester | K88: Minnesota | L88: 55901 | M88: Central | N88: TEC-AC-10001998 | O88: Technology | P88: Accessories | Q88: Logitech LS21 Speaker System - PC Multimedia - 2.1-CH - Wired | R88: 19.99 | S88: 1 | T88: 0 | U88: 6.7966 | V88: =IF(ISNUMBER(SalesData[[#This Row],[Order Date]]),DATE(YEAR(SalesData[[#This Row],[Order Date]]),DAY(SalesData[[#This Row],[Order Date]]),MONTH(SalesData[[#This Row],[Order Date]])),DATE(VALUE(RIGHT(SalesData[[#This Row],[Order Date]],4)),VALUE(LEFT(SalesData[[#This Row],[Order Date]],FIND("/",SalesData[[#This Row],[Order Date]])-1)),VALUE(MID(SalesData[[#This Row],[Order Date]],FIND("/",SalesData[[#This Row],[Order Date]])+1,FIND("/",SalesData[[#This Row],[Order Date]],FIND("/",SalesData[[#This Row],[Order Date]])+1)-FIND("/",SalesData[[#This Row],[Order Date]])-1)))) -> 43034
A89: 88 | B89: CA-2017-155558 | C89: 10/26/2017 | D89: 42777 | E89: Standard Class | F89: PG-18895 | G89: Paul Gonzalez | H89: Consumer | I89: United States | J89: Rochester | K89: Minnesota | L89: 55901 | M89: Central | N89: OFF-LA-10000134 | O89: Office Supplies | P89: Labels | Q89: Avery 511 | R89: 6.16 | S89: 2 | T89: 0 | U89: 2.9568 | V89: =IF(ISNUMBER(SalesData[[#This Row],[Order Date]]),DATE(YEAR(SalesData[[#This Row],[Order Date]]),DAY(SalesData[[#This Row],[Order Date]]),MONTH(SalesData[[#This Row],[Order Date]])),DATE(VALUE(RIGHT(SalesData[[#This Row],[Order Date]],4)),VALUE(LEFT(SalesData[[#This Row],[Order Date]],FIND("/",SalesData[[#This Row],[Order Date]])-1)),VALUE(MID(SalesData[[#This Row],[Order Date]],FIND("/",SalesData[[#This Row],[Order Date]])+1,FIND("/",SalesData[[#This Row],[Order Date]],FIND("/",SalesData[[#This Row],[Order Date]])+1)-FIND("/",SalesData[[#This Row],[Order Date]])-1)))) -> 43034
A90: 89 | B90: CA-2016-159695 | C90: 42494 | D90: 42647 | E90: Second Class | F90: GM-14455 | G90: Gary Mitchum | H90: Home Office | I90: United States | J90: Houston | K90: Texas | L90: 77095 | M90: Central | N90: OFF-ST-10003442 | O90: Office Supplies | P90: Storage | Q90: Eldon Portable Mobile Manager | R90: 158.368 | S90: 7 | T90: 0.2 | U90: 13.8572 | V90: =IF(ISNUMBER(SalesData[[#This Row],[Order Date]]),DATE(YEAR(SalesData[[#This Row],[Order Date]]),DAY(SalesData[[#This Row],[Order Date]]),MONTH(SalesData[[#This Row],[Order Date]])),DATE(VALUE(RIGHT(SalesData[[#This Row],[Order Date]],4)),VALUE(LEFT(SalesData[[#This Row],[Order Date]],FIND("/",SalesData[[#This Row],[Order Date]])-1)),VALUE(MID(SalesData[[#This Row],[Order Date]],FIND("/",SalesData[[#This Row],[Order Date]])+1,FIND("/",SalesData[[#This Row],[Order Date]],FIND("/",SalesData[[#This Row],[Order Date]])+1)-FIND("/",SalesData[[#This Row],[Order Date]])-1)))) -> 42465
A91: 90 | B91: CA-2016-109806 | C91: 9/17/2016 | D91: 9/22/2016 | E91: Standard Class | F91: JS-15685 | G91: Jim Sink | H91: Corporate | I91: United States | J91: Los Angeles | K91: California | L91: 90036 | M91: West | N91: OFF-AR-10004930 | O91: Office Supplies | P91: Art | Q91: Turquoise Lead Holder with Pocket Clip | R91: 20.1 | S91: 3 | T91: 0 | U91: 6.633 | V91: =IF(ISNUMBER(SalesData[[#This Row],[Order Date]]),DATE(YEAR(SalesData[[#This Row],[Order Date]]),DAY(SalesData[[#This Row],[Order Date]]),MONTH(SalesData[[#This Row],[Order Date]])),DATE(VALUE(RIGHT(SalesData[[#This Row],[Order Date]],4)),VALUE(LEFT(SalesData[[#This Row],[Order Date]],FIND("/",SalesData[[#This Row],[Order Date]])-1)),VALUE(MID(SalesData[[#This Row],[Order Date]],FIND("/",SalesData[[#This Row],[Order Date]])+1,FIND("/",SalesData[[#This Row],[Order Date]],FIND("/",SalesData[[#This Row],[Order Date]])+1)-FIND("/",SalesData[[#This Row],[Order Date]])-1)))) -> 42630
A92: 91 | B92: CA-2016-109806 | C92: 9/17/2016 | D92: 9/22/2016 | E92: Standard Class | F92: JS-15685 | G92: Jim Sink | H92: Corporate | I92: United States | J92: Los Angeles | K92: California | L92: 90036 | M92: West | N92: TEC-PH-10004093 | O92: Technology | P92: Phones | Q92: Panasonic Kx-TS550 | R92: 73.584 | S92: 2 | T92: 0.2 | U92: 8.2782 | V92: =IF(ISNUMBER(SalesData[[#This Row],[Order Date]]),DATE(YEAR(SalesData[[#This Row],[Order Date]]),DAY(SalesData[[#This Row],[Order Date]]),MONTH(SalesData[[#This Row],[Order Date]])),DATE(VALUE(RIGHT(SalesData[[#This Row],[Order Date]],4)),VALUE(LEFT(SalesData[[#This Row],[Order Date]],FIND("/",SalesData[[#This Row],[Order Date]])-1)),VALUE(MID(SalesData[[#This Row],[Order Date]],FIND("/",SalesData[[#This Row],[Order Date]])+1,FIND("/",SalesData[[#This Row],[Order Date]],FIND("/",SalesData[[#This Row],[Order Date]])+1)-FIND("/",SalesData[[#This Row],[Order Date]])-1)))) -> 42630
A93: 92 | B93: CA-2016-109806 | C93: 9/17/2016 | D93: 9/22/2016 | E93: Standard Class | F93: JS-15685 | G93: Jim Sink | H93: Corporate | I93: United States | J93: Los Angeles | K93: California | L93: 90036 | M93: West | N93: OFF-PA-10000304 | O93: Office Supplies | P93: Paper | Q93: Xerox 1995 | R93: 6.48 | S93: 1 | T93: 0 | U93: 3.1104 | V93: =IF(ISNUMBER(SalesData[[#This Row],[Order Date]]),DATE(YEAR(SalesData[[#This Row],[Order Date]]),DAY(SalesData[[#This Row],[Order Date]]),MONTH(SalesData[[#This Row],[Order Date]])),DATE(VALUE(RIGHT(SalesData[[#This Row],[Order Date]],4)),VALUE(LEFT(SalesData[[#This Row],[Order Date]],FIND("/",SalesData[[#This Row],[Order Date]])-1)),VALUE(MID(SalesData[[#This Row],[Order Date]],FIND("/",SalesData[[#This Row],[Order Date]])+1,FIND("/",SalesData[[#This Row],[Order Date]],FIND("/",SalesData[[#This Row],[Order Date]])+1)-FIND("/",SalesData[[#This Row],[Order Date]])-1)))) -> 42630
A94: 93 | B94: CA-2015-149587 | C94: 1/31/2015 | D94: 42126 | E94: Second Class | F94: KB-16315 | G94: Karl Braun | H94: Consumer | I94: United States | J94: Minneapolis | K94: Minnesota | L94: 55407 | M94: Central | N94: OFF-PA-10003177 | O94: Office Supplies | P94: Paper | Q94: Xerox 1999 | R94: 12.96 | S94: 2 | T94: 0 | U94: 6.2208 | V94: =IF(ISNUMBER(SalesData[[#This Row],[Order Date]]),DATE(YEAR(SalesData[[#This Row],[Order Date]]),DAY(SalesData[[#This Row],[Order Date]]),MONTH(SalesData[[#This Row],[Order Date]])),DATE(VALUE(RIGHT(SalesData[[#This Row],[Order Date]],4)),VALUE(LEFT(SalesData[[#This Row],[Order Date]],FIND("/",SalesData[[#This Row],[Order Date]])-1)),VALUE(MID(SalesData[[#This Row],[Order Date]],FIND("/",SalesData[[#This Row],[Order Date]])+1,FIND("/",SalesData[[#This Row],[Order Date]],FIND("/",SalesData[[#This Row],[Order Date]])+1)-FIND("/",SalesData[[#This Row],[Order Date]])-1)))) -> 42035
A95: 94 | B95: CA-2015-149587 | C95: 1/31/2015 | D95: 42126 | E95: Second Class | F95: KB-16315 | G95: Karl Braun | H95: Consumer | I95: United States | J95: Minneapolis | K95: Minnesota | L95: 55407 | M95: Central | N95: FUR-FU-10003799 | O95: Furniture | P95: Furnishings | Q95: Seth Thomas 13 1/2" Wall Clock | R95: 53.34 | S95: 3 | T95: 0 | U95: 16.5354 | V95: =IF(ISNUMBER(SalesData[[#This Row],[Order Date]]),DATE(YEAR(SalesData[[#This Row],[Order Date]]),DAY(SalesData[[#This Row],[Order Date]]),MONTH(SalesData[[#This Row],[Order Date]])),DATE(VALUE(RIGHT(SalesData[[#This Row],[Order Date]],4)),VALUE(LEFT(SalesData[[#This Row],[Order Date]],FIND("/",SalesData[[#This Row],[Order Date]])-1)),VALUE(MID(SalesData[[#This Row],[Order Date]],FIND("/",SalesData[[#This Row],[Order Date]])+1,FIND("/",SalesData[[#This Row],[Order Date]],FIND("/",SalesData[[#This Row],[Order Date]])+1)-FIND("/",SalesData[[#This Row],[Order Date]])-1)))) -> 42035
A96: 95 | B96: CA-2015-149587 | C96: 1/31/2015 | D96: 42126 | E96: Second Class | F96: KB-16315 | G96: Karl Braun | H96: Consumer | I96: United States | J96: Minneapolis | K96: Minnesota | L96: 55407 | M96: Central | N96: OFF-BI-10002852 | O96: Office Supplies | P96: Binders | Q96: Ibico Standard Transparent Covers | R96: 32.96 | S96: 2 | T96: 0 | U96: 16.1504 | V96: =IF(ISNUMBER(SalesData[[#This Row],[Order Date]]),DATE(YEAR(SalesData[[#This Row],[Order Date]]),DAY(SalesData[[#This Row],[Order Date]]),MONTH(SalesData[[#This Row],[Order Date]])),DATE(VALUE(RIGHT(SalesData[[#This Row],[Order Date]],4)),VALUE(LEFT(SalesData[[#This Row],[Order Date]],FIND("/",SalesData[[#This Row],[Order Date]])-1)),VALUE(MID(SalesData[[#This Row],[Order Date]],FIND("/",SalesData[[#This Row],[Order Date]])+1,FIND("/",SalesData[[#This Row],[Order Date]],FIND("/",SalesData[[#This Row],[Order Date]])+1)-FIND("/",SalesData[[#This Row],[Order Date]])-1)))) -> 42035
A97: 96 | B97: US-2017-109484 | C97: 42897 | D97: 43080 | E97: Standard Class | F97: RB-19705 | G97: Roger Barcio | H97: Home Office | I97: United States | J97: Portland | K97: Oregon | L97: 97206 | M97: West | N97: OFF-BI-10004738 | O97: Office Supplies | P97: Binders | Q97: Flexible Leather- Look Classic Collection Ring Binder | R97: 5.682 | S97: 1 | T97: 0.7 | U97: -3.788 | V97: =IF(ISNUMBER(SalesData[[#This Row],[Order Date]]),DATE(YEAR(SalesData[[#This Row],[Order Date]]),DAY(SalesData[[#This Row],[Order Date]]),MONTH(SalesData[[#This Row],[Order Date]])),DATE(VALUE(RIGHT(SalesData[[#This Row],[Order Date]],4)),VALUE(LEFT(SalesData[[#This Row],[Order Date]],FIND("/",SalesData[[#This Row],[Order Date]])-1)),VALUE(MID(SalesData[[#This Row],[Order Date]],FIND("/",SalesData[[#This Row],[Order Date]])+1,FIND("/",SalesData[[#This Row],[Order Date]],FIND("/",SalesData[[#This Row],[Order Date]])+1)-FIND("/",SalesData[[#This Row],[Order Date]])-1)))) -> 43045
A98: 97 | B98: CA-2017-161018 | C98: 42989 | D98: 43050 | E98: Second Class | F98: PN-18775 | G98: Parhena Norris | H98: Home Office | I98: United States | J98: New York City | K98: New York | L98: 10009 | M98: East | N98: FUR-FU-10000629 | O98: Furniture | P98: Furnishings | Q98: 9-3/4 Diameter Round Wall Clock | R98: 96.53 | S98: 7 | T98: 0 | U98: 40.5426 | V98: =IF(ISNUMBER(SalesData[[#This Row],[Order Date]]),DATE(YEAR(SalesData[[#This Row],[Order Date]]),DAY(SalesData[[#This Row],[Order Date]]),MONTH(SalesData[[#This Row],[Order Date]])),DATE(VALUE(RIGHT(SalesData[[#This Row],[Order Date]],4)),VALUE(LEFT(SalesData[[#This Row],[Order Date]],FIND("/",SalesData[[#This Row],[Order Date]])-1)),VALUE(MID(SalesData[[#This Row],[Order Date]],FIND("/",SalesData[[#This Row],[Order Date]])+1,FIND("/",SalesData[[#This Row],[Order Date]],FIND("/",SalesData[[#This Row],[Order Date]])+1)-FIND("/",SalesData[[#This Row],[Order Date]])-1)))) -> 43048
A99: 98 | B99: CA-2017-157833 | C99: 6/17/2017 | D99: 6/20/2017 | E99: First Class | F99: KD-16345 | G99: Katherine Ducich | H99: Consumer | I99: United States | J99: San Francisco | K99: California | L99: 94122 | M99: West | N99: OFF-BI-10001721 | O99: Office Supplies | P99: Binders | Q99: Trimflex Flexible Post Binders | R99: 51.312 | S99: 3 | T99: 0.2 | U99: 17.9592 | V99: =IF(ISNUMBER(SalesData[[#This Row],[Order Date]]),DATE(YEAR(SalesData[[#This Row],[Order Date]]),DAY(SalesData[[#This Row],[Order Date]]),MONTH(SalesData[[#This Row],[Order Date]])),DATE(VALUE(RIGHT(SalesData[[#This Row],[Order Date]],4)),VALUE(LEFT(SalesData[[#This Row],[Order Date]],FIND("/",SalesData[[#This Row],[Order Date]])-1)),VALUE(MID(SalesData[[#This Row],[Order Date]],FIND("/",SalesData[[#This Row],[Order Date]])+1,FIND("/",SalesData[[#This Row],[Order Date]],FIND("/",SalesData[[#This Row],[Order Date]])+1)-FIND("/",SalesData[[#This Row],[Order Date]])-1)))) -> 42903
A100: 99 | B100: CA-2016-149223 | C100: 42530 | D100: 42683 | E100: Standard Class | F100: ER-13855 | G100: Elpida Rittenbach | H100: Corporate | I100: United States | J100: Saint Paul | K100: Minnesota | L100: 55106 | M100: Central | N100: OFF-AP-10000358 | O100: Office Supplies | P100: Appliances | Q100: Fellowes Basic Home/Office Series Surge Protectors | R100: 77.88 | S100: 6 | T100: 0 | U100: 22.5852 | V100: =IF(ISNUMBER(SalesData[[#This Row],[Order Date]]),DATE(YEAR(SalesData[[#This Row],[Order Date]]),DAY(SalesData[[#This Row],[Order Date]]),MONTH(SalesData[[#This Row],[Order Date]])),DATE(VALUE(RIGHT(SalesData[[#This Row],[Order Date]],4)),VALUE(LEFT(SalesData[[#This Row],[Order Date]],FIND("/",SalesData[[#This Row],[Order Date]])-1)),VALUE(MID(SalesData[[#This Row],[Order Date]],FIND("/",SalesData[[#This Row],[Order Date]])+1,FIND("/",SalesData[[#This Row],[Order Date]],FIND("/",SalesData[[#This Row],[Order Date]])+1)-FIND("/",SalesData[[#This Row],[Order Date]])-1)))) -> 42619
...

Sheet Formulas Demo
A1: Excel Formulas and Functions on Superstore data.
A3: Function | B3: What I am doing | C3: Result | D3: Formula used | E3: When to use it
A4: VLOOKUP | B4: Find the Sales for Row ID 3 | C4: =VLOOKUP(3,SalesData[],18,FALSE) -> 14.62 | D4: =_xlfn.FORMULATEXT(C4) -> =VLOOKUP(3,SalesData,18,FALSE) | E4: Use when the ID is in the first column. It breaks if columns move because it needs a column number.
A5: XLOOKUP | B5: Find the Sales for Row ID 3 | C5: =_xlfn.XLOOKUP(3,SalesData[Row ID],SalesData[Sales]) -> 14.62 | D5: =_xlfn.FORMULATEXT(C5) -> =XLOOKUP(3,SalesData[Row ID],SalesData[Sales]) | E5: Newer and safer than VLOOKUP. No column number needed and it can look in any direction.
A6: INDEX/MATCH | B6: Find the Sales for Row ID 3 | C6: =INDEX(SalesData[Sales],MATCH(3,SalesData[Row ID],0)) -> 14.62 | D6: =_xlfn.FORMULATEXT(C6) -> =INDEX(SalesData[Sales],MATCH(3,SalesData[Row ID],0)) | E6: Use when XLOOKUP is not available or the lookup column is not on the left.
A7: IF | B7: Is the 4th order a profit or a loss | C7: =IF('Raw Data'!U5>0,"Profit","Loss") -> Loss | D7: =_xlfn.FORMULATEXT(C7) -> =IF('Raw Data'!U5>0,"Profit","Loss") | E7: Use for a simple yes or no decision with one condition.
A8: Nested IF | B8: Label the first sale as High, Medium or Low | C8: =IF('Raw Data'!R2>500,"High",IF('Raw Data'!R2>100,"Medium","Low")) -> Medium | D8: =_xlfn.FORMULATEXT(C8) -> =IF('Raw Data'!R2>500,"High",IF('Raw Data'!R2>100,"Medium","Low")) | E8: Use for 3 or more groups. Keep it short because too many IFs are hard to read.
A9: SUMIF | B9: Total sales of the West region | C9: =SUMIF(SalesData[Region],"West",SalesData[Sales]) -> 725457.82 | D9: =_xlfn.FORMULATEXT(C9) -> =SUMIF(SalesData[Region],"West",SalesData[Sales]) | E9: Use to add up values with ONE condition.
A10: SUMIFS | B10: West sales of the Technology category | C10: =SUMIFS(SalesData[Sales],SalesData[Region],"West",SalesData[Category],"Technology") -> 251991.83 | D10: =_xlfn.FORMULATEXT(C10) -> =SUMIFS(SalesData[Sales],SalesData[Region],"West",SalesData[Category],"Technology") | E10: Use to add up values with TWO or more conditions.
A11: COUNTIFS | B11: Count West order lines that made a loss | C11: =COUNTIFS(SalesData[Region],"West",SalesData[Profit],"<0") -> 318 | D11: =_xlfn.FORMULATEXT(C11) -> =COUNTIFS(SalesData[Region],"West",SalesData[Profit],"<0") | E11: Use to count rows that meet one or more conditions.
A12: AVERAGEIFS | B12: Average discount in the Central region | C12: =AVERAGEIFS(SalesData[Discount],SalesData[Region],"Central") -> 0.24035299 | D12: =_xlfn.FORMULATEXT(C12) -> =AVERAGEIFS(SalesData[Discount],SalesData[Region],"Central") | E12: Use to find the average of a group.
A13: UPPER | B13: First customer name in capital letters | C13: =UPPER('Raw Data'!G2) -> CLAIRE GUTE | D13: =_xlfn.FORMULATEXT(C13) -> =UPPER('Raw Data'!G2) | E13: Use to make text consistent in capital letters.
A14: LEFT + FIND | B14: Get the first name of the first customer | C14: =LEFT('Raw Data'!G2,FIND(" ",'Raw Data'!G2)-1) -> Claire | D14: =_xlfn.FORMULATEXT(C14) -> =LEFT('Raw Data'!G2,FIND(" ",'Raw Data'!G2)-1) | E14: Use to cut part of a text, like a first name.
A15: TRIM + PROPER | B15: Clean a messy name with extra spaces | C15: =PROPER(TRIM(" claire gute ")) -> Claire Gute | D15: =_xlfn.FORMULATEXT(C15) -> =PROPER(TRIM(" claire gute ")) | E15: Use to clean messy text with extra spaces and wrong capitals.
A16: CONCAT | B16: Join the Order ID and customer name | C16: =_xlfn.CONCAT('Raw Data'!B2," - ",'Raw Data'!G2) -> CA-2016-152156 - Claire Gute | D16: =_xlfn.FORMULATEXT(C16) -> =CONCAT('Raw Data'!B2," - ",'Raw Data'!G2) | E16: Use to join text from different cells.
A17: LEN | B17: Count the characters in the first customer name | C17: =LEN('Raw Data'!G2) -> 11 | D17: =_xlfn.FORMULATEXT(C17) -> =LEN('Raw Data'!G2) | E17: Use to count characters, for example to check ID lengths.
A18: IFERROR (not found) | B18: Look up a Row ID that does not exist | C18: =IFERROR(VLOOKUP(99999,SalesData[],18,FALSE),"Not found") -> Not found | D18: =_xlfn.FORMULATEXT(C18) -> =IFERROR(VLOOKUP(99999,SalesData,18,FALSE),"Not found") | E18: Use to show a friendly message instead of an error.
A19: Text vs number mismatch | B19: Look up the number 3 typed as text | C19: =IFERROR(VLOOKUP("3",SalesData[],18,FALSE),"Mismatch: text vs number") -> Mismatch: text vs number | D19: =_xlfn.FORMULATEXT(C19) -> =IFERROR(VLOOKUP("3",SalesData,18,FALSE),"Mismatch: text vs number") | E19: A lookup fails when one side is text and the other is a number. Convert one of them so they match.
A20: IF + blank cell | B20: Check an empty cell | C20: =IF(Z1="","Blank cell","Has value") -> Blank cell | D20: =_xlfn.FORMULATEXT(C20) -> =IF(Z1="","Blank cell","Has value") | E20: Use to catch empty cells before they break a calculation.
